Workbook

Sheet data
A1: QLI Number | B1: document_id | C1: currency | D1: customer_name | E1: deal_number | F1: document_name | G1: document_type | H1: entity | I1: invoice_date | J1: invoice_number | K1: legal_customer_name | L1: media_reference | M1: payment_term | N1: Po Number | O1: project_name | P1: supplier_name | Q1: total_invoice_amount | R1: vendor_name | S1: vsow_number | T1: __is_deleted | U1: __patch_offset | V1: vsow_document_id | W1: vsow_currency | X1: vsow_customer_name | Y1: vsow_deal_number | Z1: vsow_document_name | AA1: vsow_media_reference | AB1: vsow_payment_term | AC1: vsow_po_number | AD1: vsow_project_name | AE1: vsow_supplier_name | AF1: vsow_total_cost | AG1: vsow_total_cost_numeric | AH1: vsow_vsow_number | AI1: vsow___is_deleted | AJ1: vsow___patch_offset | AK1: line_item_primary_key_ | AL1: line_item_address | AM1: line_item_arc | AN1: line_item_bill_feature | AO1: line_item_billing_id | AP1: Item Description | AQ1: line_item_charge_type | AR1: line_item_city | AS1: line_item_correction_reasoning | AT1: line_item_customer | AU1: line_item_discount | AV1: line_item_document_rid | AW1: line_item_document_type | AX1: line_item_equipment_cost | AY1: line_item_expected_line_item_match_reasoning | AZ1: line_item_expected_line_item_match_status | BA1: line_item_in_evals | BB1: line_item_is_extraction_validated | BC1: line_item_is_mapping_validated | BD1: Item Code | BE1: line_item_item_description | BF1: line_item_last_validation_timestamp | BG1: line_item_last_validation_timestamp_tz | BH1: line_item_make | BI1: line_item_model | BJ1: MRC | BK1: line_item_needs_review | BL1: NRC | BM1: line_item_oem | BN1: OTC | BO1: line_item_page_number | BP1: line_item_page_rid | BQ1: line_item_part_number | BR1: line_item_previous_month_mrc | BS1: line_item_qrc_unit | BT1: Quantity | BU1: line_item_row_number | BV1: serial_number | BW1: line_item_service_end_date | BX1: line_item_service_start_date | BY1: line_item_sheet_name | BZ1: Site Id | CA1: line_item_site_name | CB1: line_item_state | CC1: line_item_status | CD1: line_item_support_cost | CE1: line_item_tax_amount | CF1: line_item_tax_percentage | CG1: line_item_tenure | CH1: line_item_total_amount | CI1: line_item_total_mrc | CJ1: line_item_total_otc_nrc_value | CK1: UP | CL1: line_item_zip | CM1: line_item___is_deleted | CN1: line_item___patch_offset
A2: QLI00001 | B2: ri.mio.main.media-item.0199713b-dbcf-7ebd-9cc7-6e4ba33fe6f4 | C2: CAD | D2: Equinix Canada, Ltd. | F2: Quote2-PO3000196864-EQUINIX-ATT+Wipro+Canada_Renewal+Post-Novation+(7+Months)__Quote_Num_1-223208968420+ATT+Sign+20230124.pdf | G2: Quote | H2: AT&T | L2: {"mimeType":"application/pdf","reference":{"type":"mediaSetViewItem","mediaSetViewItem":{"mediaSetRid":"ri.mio.main.media-set.7a7aadd5-adcf-42ac-9e71-12078d56f27e","mediaSetViewRid":"ri.mio.main.view.5660cab0-05c2-4700-94bc-c64529e38113","mediaItemRid":"ri.mio.main.media-item.0199713b-dbcf-7ebd-9cc7-6e4ba33fe6f4"}}} | N2: PO3000196864 | P2: Equinix Canada, Ltd. | T2: FALSE | U2: -1 | AK2: ri.mio.main.media-item.0199713b-dbcf-7ebd-9cc7-6e4ba33fe6f4_1_1 | AP2: Private Cage With KVA Based Power | AV2: ri.mio.main.media-item.0199713b-dbcf-7ebd-9cc7-6e4ba33fe6f4 | AW2: Quote | BD2: SPC00002 | BJ2: 30316 | BL2: 0 | BO2: 1 | BP2: ri.mio.main.media-item.0199713b-dbcf-7ebd-9cc7-6e4ba33fe6f4_0 | BT2: 1 | BU2: 1 | BV2: 7-100000400339 | BX2: 44896 | BZ2: MT1 | CA2: MT1 | CI2: 30316 | CM2: FALSE | CN2: 37290
A3: QLI00002 | B3: ri.mio.main.media-item.0199713b-dbcf-7ebd-9cc7-6e4ba33fe6f4 | C3: CAD | D3: Equinix Canada, Ltd. | F3: Quote2-PO3000196864-EQUINIX-ATT+Wipro+Canada_Renewal+Post-Novation+(7+Months)__Quote_Num_1-223208968420+ATT+Sign+20230124.pdf | G3: Quote | H3: AT&T | L3: {"mimeType":"application/pdf","reference":{"type":"mediaSetViewItem","mediaSetViewItem":{"mediaSetRid":"ri.mio.main.media-set.7a7aadd5-adcf-42ac-9e71-12078d56f27e","mediaSetViewRid":"ri.mio.main.view.5660cab0-05c2-4700-94bc-c64529e38113","mediaItemRid":"ri.mio.main.media-item.0199713b-dbcf-7ebd-9cc7-6e4ba33fe6f4"}}} | N3: PO3000196864 | P3: Equinix Canada, Ltd. | T3: FALSE | U3: -1 | AK3: ri.mio.main.media-item.0199713b-dbcf-7ebd-9cc7-6e4ba33fe6f4_1_2 | AP3: Cage - Customer Provided Cabinet - 12 Cabinets - 53 KVA | AV3: ri.mio.main.media-item.0199713b-dbcf-7ebd-9cc7-6e4ba33fe6f4 | AW3: Quote | BD3: CAG00001 | BJ3: 0 | BL3: 15158 | BO3: 1 | BP3: ri.mio.main.media-item.0199713b-dbcf-7ebd-9cc7-6e4ba33fe6f4_0 | BT3: 53 | BU3: 2 | BV3: 0811814 | BX3: 44896 | BZ3: MT1 | CA3: MT1 | CI3: 0 | CM3: FALSE | CN3: 37290
A4: QLI00003 | B4: ri.mio.main.media-item.0199713b-dbcf-7ebd-9cc7-6e4ba33fe6f4 | C4: CAD | D4: Equinix Canada, Ltd. | F4: Quote2-PO3000196864-EQUINIX-ATT+Wipro+Canada_Renewal+Post-Novation+(7+Months)__Quote_Num_1-223208968420+ATT+Sign+20230124.pdf | G4: Quote | H4: AT&T | L4: {"mimeType":"application/pdf","reference":{"type":"mediaSetViewItem","mediaSetViewItem":{"mediaSetRid":"ri.mio.main.media-set.7a7aadd5-adcf-42ac-9e71-12078d56f27e","mediaSetViewRid":"ri.mio.main.view.5660cab0-05c2-4700-94bc-c64529e38113","mediaItemRid":"ri.mio.main.media-item.0199713b-dbcf-7ebd-9cc7-6e4ba33fe6f4"}}} | N4: PO3000196864 | P4: Equinix Canada, Ltd. | T4: FALSE | U4: -1 | AK4: ri.mio.main.media-item.0199713b-dbcf-7ebd-9cc7-6e4ba33fe6f4_1_3 | AP4: AC Power | AV4: ri.mio.main.media-item.0199713b-dbcf-7ebd-9cc7-6e4ba33fe6f4 | AW4: Quote | BD4: POW00001 | BJ4: 0 | BL4: 15158 | BO4: 1 | BP4: ri.mio.main.media-item.0199713b-dbcf-7ebd-9cc7-6e4ba33fe6f4_0 | BT4: 53 | BU4: 3 | BV4: 7-100000401078 | BX4: 44896 | BZ4: MT1 | CA4: MT1 | CI4: 0 | CM4: FALSE | CN4: 37290
A5: QLI00004 | B5: ri.mio.main.media-item.0199713b-dbcf-7ebd-9cc7-6e4ba33fe6f4 | C5: CAD | D5: Equinix Canada, Ltd. | F5: Quote2-PO3000196864-EQUINIX-ATT+Wipro+Canada_Renewal+Post-Novation+(7+Months)__Quote_Num_1-223208968420+ATT+Sign+20230124.pdf | G5: Quote | H5: AT&T | L5: {"mimeType":"application/pdf","reference":{"type":"mediaSetViewItem","mediaSetViewItem":{"mediaSetRid":"ri.mio.main.media-set.7a7aadd5-adcf-42ac-9e71-12078d56f27e","mediaSetViewRid":"ri.mio.main.view.5660cab0-05c2-4700-94bc-c64529e38113","mediaItemRid":"ri.mio.main.media-item.0199713b-dbcf-7ebd-9cc7-6e4ba33fe6f4"}}} | N5: PO3000196864 | P5: Equinix Canada, Ltd. | T5: FALSE | U5: -1 | AK5: ri.mio.main.media-item.0199713b-dbcf-7ebd-9cc7-6e4ba33fe6f4_2_1 | AP5: AC Circuit - 208v - 20-amp - Three Phase - Redundant | AV5: ri.mio.main.media-item.0199713b-dbcf-7ebd-9cc7-6e4ba33fe6f4 | AW5: Quote | BD5: POW00003 | BJ5: 0 | BO5: 2 | BP5: ri.mio.main.media-item.0199713b-dbcf-7ebd-9cc7-6e4ba33fe6f4_1 | BT5: 1 | BU5: 1 | BV5: 100247282.MT1 | BX5: 44896 | CI5: 0 | CM5: FALSE | CN5: 33590
A6: QLI00005 | B6: ri.mio.main.media-item.0199713b-dbcf-7ebd-9cc7-6e4ba33fe6f4 | C6: CAD | D6: Equinix Canada, Ltd. | F6: Quote2-PO3000196864-EQUINIX-ATT+Wipro+Canada_Renewal+Post-Novation+(7+Months)__Quote_Num_1-223208968420+ATT+Sign+20230124.pdf | G6: Quote | H6: AT&T | L6: {"mimeType":"application/pdf","reference":{"type":"mediaSetViewItem","mediaSetViewItem":{"mediaSetRid":"ri.mio.main.media-set.7a7aadd5-adcf-42ac-9e71-12078d56f27e","mediaSetViewRid":"ri.mio.main.view.5660cab0-05c2-4700-94bc-c64529e38113","mediaItemRid":"ri.mio.main.media-item.0199713b-dbcf-7ebd-9cc7-6e4ba33fe6f4"}}} | N6: PO3000196864 | P6: Equinix Canada, Ltd. | T6: FALSE | U6: -1 | AK6: ri.mio.main.media-item.0199713b-dbcf-7ebd-9cc7-6e4ba33fe6f4_2_10 | AP6: Cabinet - 3.53 kVA - Open Cabinet | AV6: ri.mio.main.media-item.0199713b-dbcf-7ebd-9cc7-6e4ba33fe6f4 | AW6: Quote | BD6: CAB00001 | BJ6: 0 | BO6: 2 | BP6: ri.mio.main.media-item.0199713b-dbcf-7ebd-9cc7-6e4ba33fe6f4_1 | BT6: 1 | BU6: 10 | BV6: 0204-00121279 | BX6: 44896 | CI6: 0 | CM6: FALSE | CN6: 33590
A7: QLI00006 | B7: ri.mio.main.media-item.0199713b-dbcf-7ebd-9cc7-6e4ba33fe6f4 | C7: CAD | D7: Equinix Canada, Ltd. | F7: Quote2-PO3000196864-EQUINIX-ATT+Wipro+Canada_Renewal+Post-Novation+(7+Months)__Quote_Num_1-223208968420+ATT+Sign+20230124.pdf | G7: Quote | H7: AT&T | L7: {"mimeType":"application/pdf","reference":{"type":"mediaSetViewItem","mediaSetViewItem":{"mediaSetRid":"ri.mio.main.media-set.7a7aadd5-adcf-42ac-9e71-12078d56f27e","mediaSetViewRid":"ri.mio.main.view.5660cab0-05c2-4700-94bc-c64529e38113","mediaItemRid":"ri.mio.main.media-item.0199713b-dbcf-7ebd-9cc7-6e4ba33fe6f4"}}} | N7: PO3000196864 | P7: Equinix Canada, Ltd. | T7: FALSE | U7: -1 | AK7: ri.mio.main.media-item.0199713b-dbcf-7ebd-9cc7-6e4ba33fe6f4_2_11 | AP7: Cabinet - 3.53 kVA - Open Cabinet | AV7: ri.mio.main.media-item.0199713b-dbcf-7ebd-9cc7-6e4ba33fe6f4 | AW7: Quote | BD7: CAB00001 | BJ7: 0 | BO7: 2 | BP7: ri.mio.main.media-item.0199713b-dbcf-7ebd-9cc7-6e4ba33fe6f4_1 | BT7: 1 | BU7: 11 | BV7: 0201-00121276 | BX7: 44896 | CI7: 0 | CM7: FALSE | CN7: 33590
A8: QLI00007 | B8: ri.mio.main.media-item.0199713b-dbcf-7ebd-9cc7-6e4ba33fe6f4 | C8: CAD | D8: Equinix Canada, Ltd. | F8: Quote2-PO3000196864-EQUINIX-ATT+Wipro+Canada_Renewal+Post-Novation+(7+Months)__Quote_Num_1-223208968420+ATT+Sign+20230124.pdf | G8: Quote | H8: AT&T | L8: {"mimeType":"application/pdf","reference":{"type":"mediaSetViewItem","mediaSetViewItem":{"mediaSetRid":"ri.mio.main.media-set.7a7aadd5-adcf-42ac-9e71-12078d56f27e","mediaSetViewRid":"ri.mio.main.view.5660cab0-05c2-4700-94bc-c64529e38113","mediaItemRid":"ri.mio.main.media-item.0199713b-dbcf-7ebd-9cc7-6e4ba33fe6f4"}}} | N8: PO3000196864 | P8: Equinix Canada, Ltd. | T8: FALSE | U8: -1 | AK8: ri.mio.main.media-item.0199713b-dbcf-7ebd-9cc7-6e4ba33fe6f4_2_12 | AP8: Cabinet - 3.53 kVA - Open Cabinet | AV8: ri.mio.main.media-item.0199713b-dbcf-7ebd-9cc7-6e4ba33fe6f4 | AW8: Quote | BD8: CAB00001 | BJ8: 0 | BO8: 2 | BP8: ri.mio.main.media-item.0199713b-dbcf-7ebd-9cc7-6e4ba33fe6f4_1 | BT8: 1 | BU8: 12 | BV8: 0126-00121273 | BX8: 44896 | CI8: 0 | CM8: FALSE | CN8: 33590
A9: QLI00008 | B9: ri.mio.main.media-item.0199713b-dbcf-7ebd-9cc7-6e4ba33fe6f4 | C9: CAD | D9: Equinix Canada, Ltd. | F9: Quote2-PO3000196864-EQUINIX-ATT+Wipro+Canada_Renewal+Post-Novation+(7+Months)__Quote_Num_1-223208968420+ATT+Sign+20230124.pdf | G9: Quote | H9: AT&T | L9: {"mimeType":"application/pdf","reference":{"type":"mediaSetViewItem","mediaSetViewItem":{"mediaSetRid":"ri.mio.main.media-set.7a7aadd5-adcf-42ac-9e71-12078d56f27e","mediaSetViewRid":"ri.mio.main.view.5660cab0-05c2-4700-94bc-c64529e38113","mediaItemRid":"ri.mio.main.media-item.0199713b-dbcf-7ebd-9cc7-6e4ba33fe6f4"}}} | N9: PO3000196864 | P9: Equinix Canada, Ltd. | T9: FALSE | U9: -1 | AK9: ri.mio.main.media-item.0199713b-dbcf-7ebd-9cc7-6e4ba33fe6f4_2_13 | AP9: Cabinet - 3.53 kVA - Open Cabinet | AV9: ri.mio.main.media-item.0199713b-dbcf-7ebd-9cc7-6e4ba33fe6f4 | AW9: Quote | BD9: CAB00001 | BJ9: 0 | BO9: 2 | BP9: ri.mio.main.media-item.0199713b-dbcf-7ebd-9cc7-6e4ba33fe6f4_1 | BT9: 1 | BU9: 13 | BV9: 0209-00121278 | BX9: 44896 | CI9: 0 | CM9: FALSE | CN9: 33590
A10: QLI00009 | B10: ri.mio.main.media-item.0199713b-dbcf-7ebd-9cc7-6e4ba33fe6f4 | C10: CAD | D10: Equinix Canada, Ltd. | F10: Quote2-PO3000196864-EQUINIX-ATT+Wipro+Canada_Renewal+Post-Novation+(7+Months)__Quote_Num_1-223208968420+ATT+Sign+20230124.pdf | G10: Quote | H10: AT&T | L10: {"mimeType":"application/pdf","reference":{"type":"mediaSetViewItem","mediaSetViewItem":{"mediaSetRid":"ri.mio.main.media-set.7a7aadd5-adcf-42ac-9e71-12078d56f27e","mediaSetViewRid":"ri.mio.main.view.5660cab0-05c2-4700-94bc-c64529e38113","mediaItemRid":"ri.mio.main.media-item.0199713b-dbcf-7ebd-9cc7-6e4ba33fe6f4"}}} | N10: PO3000196864 | P10: Equinix Canada, Ltd. | T10: FALSE | U10: -1 | AK10: ri.mio.main.media-item.0199713b-dbcf-7ebd-9cc7-6e4ba33fe6f4_2_14 | AP10: Demarcation Point | AV10: ri.mio.main.media-item.0199713b-dbcf-7ebd-9cc7-6e4ba33fe6f4 | AW10: Quote | BD10: CC00004 | BJ10: 0 | BO10: 2 | BP10: ri.mio.main.media-item.0199713b-dbcf-7ebd-9cc7-6e4ba33fe6f4_1 | BT10: 1 | BU10: 14 | BV10: 0000-00726560 | BX10: 44896 | CI10: 0 | CM10: FALSE | CN10: 33590
A11: QLI00010 | B11: ri.mio.main.media-item.0199713b-dbcf-7ebd-9cc7-6e4ba33fe6f4 | C11: CAD | D11: Equinix Canada, Ltd. | F11: Quote2-PO3000196864-EQUINIX-ATT+Wipro+Canada_Renewal+Post-Novation+(7+Months)__Quote_Num_1-223208968420+ATT+Sign+20230124.pdf | G11: Quote | H11: AT&T | L11: {"mimeType":"application/pdf","reference":{"type":"mediaSetViewItem","mediaSetViewItem":{"mediaSetRid":"ri.mio.main.media-set.7a7aadd5-adcf-42ac-9e71-12078d56f27e","mediaSetViewRid":"ri.mio.main.view.5660cab0-05c2-4700-94bc-c64529e38113","mediaItemRid":"ri.mio.main.media-item.0199713b-dbcf-7ebd-9cc7-6e4ba33fe6f4"}}} | N11: PO3000196864 | P11: Equinix Canada, Ltd. | T11: FALSE | U11: -1 | AK11: ri.mio.main.media-item.0199713b-dbcf-7ebd-9cc7-6e4ba33fe6f4_2_15 | AP11: Cabinet - 3.53 kVA - Open Cabinet | AV11: ri.mio.main.media-item.0199713b-dbcf-7ebd-9cc7-6e4ba33fe6f4 | AW11: Quote | BD11: CAB00001 | BJ11: 0 | BO11: 2 | BP11: ri.mio.main.media-item.0199713b-dbcf-7ebd-9cc7-6e4ba33fe6f4_1 | BT11: 1 | BU11: 15 | BV11: 0301-00121280 | BX11: 44896 | CI11: 0 | CM11: FALSE | CN11: 33590
A12: QLI00011 | B12: ri.mio.main.media-item.0199713b-dbcf-7ebd-9cc7-6e4ba33fe6f4 | C12: CAD | D12: Equinix Canada, Ltd. | F12: Quote2-PO3000196864-EQUINIX-ATT+Wipro+Canada_Renewal+Post-Novation+(7+Months)__Quote_Num_1-223208968420+ATT+Sign+20230124.pdf | G12: Quote | H12: AT&T | L12: {"mimeType":"application/pdf","reference":{"type":"mediaSetViewItem","mediaSetViewItem":{"mediaSetRid":"ri.mio.main.media-set.7a7aadd5-adcf-42ac-9e71-12078d56f27e","mediaSetViewRid":"ri.mio.main.view.5660cab0-05c2-4700-94bc-c64529e38113","mediaItemRid":"ri.mio.main.media-item.0199713b-dbcf-7ebd-9cc7-6e4ba33fe6f4"}}} | N12: PO3000196864 | P12: Equinix Canada, Ltd. | T12: FALSE | U12: -1 | AK12: ri.mio.main.media-item.0199713b-dbcf-7ebd-9cc7-6e4ba33fe6f4_2_16 | AP12: Cross Connect | AV12: ri.mio.main.media-item.0199713b-dbcf-7ebd-9cc7-6e4ba33fe6f4 | AW12: Quote | BD12: CC00001 | BJ12: 320 | BO12: 2 | BP12: ri.mio.main.media-item.0199713b-dbcf-7ebd-9cc7-6e4ba33fe6f4_1 | BT12: 1 | BU12: 16 | BV12: 7-10000394303 | BX12: 44896 | CI12: 320 | CM12: FALSE | CN12: 33590
A13: QLI00012 | B13: ri.mio.main.media-item.0199713b-dbcf-7ebd-9cc7-6e4ba33fe6f4 | C13: CAD | D13: Equinix Canada, Ltd. | F13: Quote2-PO3000196864-EQUINIX-ATT+Wipro+Canada_Renewal+Post-Novation+(7+Months)__Quote_Num_1-223208968420+ATT+Sign+20230124.pdf | G13: Quote | H13: AT&T | L13: {"mimeType":"application/pdf","reference":{"type":"mediaSetViewItem","mediaSetViewItem":{"mediaSetRid":"ri.mio.main.media-set.7a7aadd5-adcf-42ac-9e71-12078d56f27e","mediaSetViewRid":"ri.mio.main.view.5660cab0-05c2-4700-94bc-c64529e38113","mediaItemRid":"ri.mio.main.media-item.0199713b-dbcf-7ebd-9cc7-6e4ba33fe6f4"}}} | N13: PO3000196864 | P13: Equinix Canada, Ltd. | T13: FALSE | U13: -1 | AK13: ri.mio.main.media-item.0199713b-dbcf-7ebd-9cc7-6e4ba33fe6f4_2_17 | AP13: Network Cable Connection - POTS - Z-side IBX- MT1 | AV13: ri.mio.main.media-item.0199713b-dbcf-7ebd-9cc7-6e4ba33fe6f4 | AW13: Quote | BD13: CC00001 | BJ13: 320 | BO13: 2 | BP13: ri.mio.main.media-item.0199713b-dbcf-7ebd-9cc7-6e4ba33fe6f4_1 | BT13: 1 | BU13: 17 | BV13: 100168372 | BX13: 44896 | BZ13: MT1 | CI13: 320 | CM13: FALSE | CN13: 33590
A14: QLI00013 | B14: ri.mio.main.media-item.0199713b-dbcf-7ebd-9cc7-6e4ba33fe6f4 | C14: CAD | D14: Equinix Canada, Ltd. | F14: Quote2-PO3000196864-EQUINIX-ATT+Wipro+Canada_Renewal+Post-Novation+(7+Months)__Quote_Num_1-223208968420+ATT+Sign+20230124.pdf | G14: Quote | H14: AT&T | L14: {"mimeType":"application/pdf","reference":{"type":"mediaSetViewItem","mediaSetViewItem":{"mediaSetRid":"ri.mio.main.media-set.7a7aadd5-adcf-42ac-9e71-12078d56f27e","mediaSetViewRid":"ri.mio.main.view.5660cab0-05c2-4700-94bc-c64529e38113","mediaItemRid":"ri.mio.main.media-item.0199713b-dbcf-7ebd-9cc7-6e4ba33fe6f4"}}} | N14: PO3000196864 | P14: Equinix Canada, Ltd. | T14: FALSE | U14: -1 | AK14: ri.mio.main.media-item.0199713b-dbcf-7ebd-9cc7-6e4ba33fe6f4_2_18 | AP14: Configurable Accessories | AV14: ri.mio.main.media-item.0199713b-dbcf-7ebd-9cc7-6e4ba33fe6f4 | AW14: Quote | BD14: PS00004 | BJ14: 0 | BL14: 0 | BO14: 2 | BP14: ri.mio.main.media-item.0199713b-dbcf-7ebd-9cc7-6e4ba33fe6f4_1 | BT14: 1 | BU14: 18 | BV14: 7-10000800310 | BX14: 44896 | CI14: 30636 | CM14: FALSE | CN14: 33590
A15: QLI00014 | B15: ri.mio.main.media-item.0199713b-dbcf-7ebd-9cc7-6e4ba33fe6f4 | C15: CAD | D15: Equinix Canada, Ltd. | F15: Quote2-PO3000196864-EQUINIX-ATT+Wipro+Canada_Renewal+Post-Novation+(7+Months)__Quote_Num_1-223208968420+ATT+Sign+20230124.pdf | G15: Quote | H15: AT&T | L15: {"mimeType":"application/pdf","reference":{"type":"mediaSetViewItem","mediaSetViewItem":{"mediaSetRid":"ri.mio.main.media-set.7a7aadd5-adcf-42ac-9e71-12078d56f27e","mediaSetViewRid":"ri.mio.main.view.5660cab0-05c2-4700-94bc-c64529e38113","mediaItemRid":"ri.mio.main.media-item.0199713b-dbcf-7ebd-9cc7-6e4ba33fe6f4"}}} | N15: PO3000196864 | P15: Equinix Canada, Ltd. | T15: FALSE | U15: -1 | AK15: ri.mio.main.media-item.0199713b-dbcf-7ebd-9cc7-6e4ba33fe6f4_2_19 | AP15: Patch Panel | AV15: ri.mio.main.media-item.0199713b-dbcf-7ebd-9cc7-6e4ba33fe6f4 | AW15: Quote | BD15: CC00001 | BL15: 200 | BO15: 2 | BP15: ri.mio.main.media-item.0199713b-dbcf-7ebd-9cc7-6e4ba33fe6f4_1 | BT15: 1 | BU15: 19 | BV15: PWP-000-1000529 | BX15: 44896 | CI15: 0 | CM15: FALSE | CN15: 33590
A16: QLI00015 | B16: ri.mio.main.media-item.0199713b-dbcf-7ebd-9cc7-6e4ba33fe6f4 | C16: CAD | D16: Equinix Canada, Ltd. | F16: Quote2-PO3000196864-EQUINIX-ATT+Wipro+Canada_Renewal+Post-Novation+(7+Months)__Quote_Num_1-223208968420+ATT+Sign+20230124.pdf | G16: Quote | H16: AT&T | L16: {"mimeType":"application/pdf","reference":{"type":"mediaSetViewItem","mediaSetViewItem":{"mediaSetRid":"ri.mio.main.media-set.7a7aadd5-adcf-42ac-9e71-12078d56f27e","mediaSetViewRid":"ri.mio.main.view.5660cab0-05c2-4700-94bc-c64529e38113","mediaItemRid":"ri.mio.main.media-item.0199713b-dbcf-7ebd-9cc7-6e4ba33fe6f4"}}} | N16: PO3000196864 | P16: Equinix Canada, Ltd. | T16: FALSE | U16: -1 | AK16: ri.mio.main.media-item.0199713b-dbcf-7ebd-9cc7-6e4ba33fe6f4_2_2 | AP16: AC Circuit - 208v - 20-amp - Three Phase - Redundant | AV16: ri.mio.main.media-item.0199713b-dbcf-7ebd-9cc7-6e4ba33fe6f4 | AW16: Quote | BD16: POW00003 | BJ16: 0 | BO16: 2 | BP16: ri.mio.main.media-item.0199713b-dbcf-7ebd-9cc7-6e4ba33fe6f4_1 | BT16: 1 | BU16: 2 | BV16: 100247288.MT1 | BX16: 44896 | CI16: 0 | CM16: FALSE | CN16: 33590
A17: QLI00016 | B17: ri.mio.main.media-item.0199713b-dbcf-7ebd-9cc7-6e4ba33fe6f4 | C17: CAD | D17: Equinix Canada, Ltd. | F17: Quote2-PO3000196864-EQUINIX-ATT+Wipro+Canada_Renewal+Post-Novation+(7+Months)__Quote_Num_1-223208968420+ATT+Sign+20230124.pdf | G17: Quote | H17: AT&T | L17: {"mimeType":"application/pdf","reference":{"type":"mediaSetViewItem","mediaSetViewItem":{"mediaSetRid":"ri.mio.main.media-set.7a7aadd5-adcf-42ac-9e71-12078d56f27e","mediaSetViewRid":"ri.mio.main.view.5660cab0-05c2-4700-94bc-c64529e38113","mediaItemRid":"ri.mio.main.media-item.0199713b-dbcf-7ebd-9cc7-6e4ba33fe6f4"}}} | N17: PO3000196864 | P17: Equinix Canada, Ltd. | T17: FALSE | U17: -1 | AK17: ri.mio.main.media-item.0199713b-dbcf-7ebd-9cc7-6e4ba33fe6f4_2_20 | AP17: Configurable Accessories | AV17: ri.mio.main.media-item.0199713b-dbcf-7ebd-9cc7-6e4ba33fe6f4 | AW17: Quote | BD17: PS00004 | BJ17: 0 | BL17: 0 | BO17: 2 | BP17: ri.mio.main.media-item.0199713b-dbcf-7ebd-9cc7-6e4ba33fe6f4_1 | BT17: 1 | BU17: 20 | BV17: 7-10000837239 | BX17: 44896 | CM17: FALSE | CN17: 33590
A18: QLI00017 | B18: ri.mio.main.media-item.0199713b-dbcf-7ebd-9cc7-6e4ba33fe6f4 | C18: CAD | D18: Equinix Canada, Ltd. | F18: Quote2-PO3000196864-EQUINIX-ATT+Wipro+Canada_Renewal+Post-Novation+(7+Months)__Quote_Num_1-223208968420+ATT+Sign+20230124.pdf | G18: Quote | H18: AT&T | L18: {"mimeType":"application/pdf","reference":{"type":"mediaSetViewItem","mediaSetViewItem":{"mediaSetRid":"ri.mio.main.media-set.7a7aadd5-adcf-42ac-9e71-12078d56f27e","mediaSetViewRid":"ri.mio.main.view.5660cab0-05c2-4700-94bc-c64529e38113","mediaItemRid":"ri.mio.main.media-item.0199713b-dbcf-7ebd-9cc7-6e4ba33fe6f4"}}} | N18: PO3000196864 | P18: Equinix Canada, Ltd. | T18: FALSE | U18: -1 | AK18: ri.mio.main.media-item.0199713b-dbcf-7ebd-9cc7-6e4ba33fe6f4_2_21 | AP18: Patch Panel | AV18: ri.mio.main.media-item.0199713b-dbcf-7ebd-9cc7-6e4ba33fe6f4 | AW18: Quote | BD18: CC00001 | BL18: 0 | BO18: 2 | BP18: ri.mio.main.media-item.0199713b-dbcf-7ebd-9cc7-6e4ba33fe6f4_1 | BT18: 1 | BU18: 21 | BV18: PP-0303:13870772 | BX18: 44896 | CI18: 0 | CM18: FALSE | CN18: 33590
A19: QLI00018 | B19: ri.mio.main.media-item.0199713b-dbcf-7ebd-9cc7-6e4ba33fe6f4 | C19: CAD | D19: Equinix Canada, Ltd. | F19: Quote2-PO3000196864-EQUINIX-ATT+Wipro+Canada_Renewal+Post-Novation+(7+Months)__Quote_Num_1-223208968420+ATT+Sign+20230124.pdf | G19: Quote | H19: AT&T | L19: {"mimeType":"application/pdf","reference":{"type":"mediaSetViewItem","mediaSetViewItem":{"mediaSetRid":"ri.mio.main.media-set.7a7aadd5-adcf-42ac-9e71-12078d56f27e","mediaSetViewRid":"ri.mio.main.view.5660cab0-05c2-4700-94bc-c64529e38113","mediaItemRid":"ri.mio.main.media-item.0199713b-dbcf-7ebd-9cc7-6e4ba33fe6f4"}}} | N19: PO3000196864 | P19: Equinix Canada, Ltd. | T19: FALSE | U19: -1 | AK19: ri.mio.main.media-item.0199713b-dbcf-7ebd-9cc7-6e4ba33fe6f4_2_22 | AP19: Patch Panel | AV19: ri.mio.main.media-item.0199713b-dbcf-7ebd-9cc7-6e4ba33fe6f4 | AW19: Quote | BD19: CC00001 | BL19: 0 | BO19: 2 | BP19: ri.mio.main.media-item.0199713b-dbcf-7ebd-9cc7-6e4ba33fe6f4_1 | BT19: 1 | BU19: 22 | BV19: PP-0303:13870771 | BX19: 44896 | CI19: 0 | CM19: FALSE | CN19: 33590
A20: QLI00019 | B20: ri.mio.main.media-item.0199713b-dbcf-7ebd-9cc7-6e4ba33fe6f4 | C20: CAD | D20: Equinix Canada, Ltd. | F20: Quote2-PO3000196864-EQUINIX-ATT+Wipro+Canada_Renewal+Post-Novation+(7+Months)__Quote_Num_1-223208968420+ATT+Sign+20230124.pdf | G20: Quote | H20: AT&T | L20: {"mimeType":"application/pdf","reference":{"type":"mediaSetViewItem","mediaSetViewItem":{"mediaSetRid":"ri.mio.main.media-set.7a7aadd5-adcf-42ac-9e71-12078d56f27e","mediaSetViewRid":"ri.mio.main.view.5660cab0-05c2-4700-94bc-c64529e38113","mediaItemRid":"ri.mio.main.media-item.0199713b-dbcf-7ebd-9cc7-6e4ba33fe6f4"}}} | N20: PO3000196864 | P20: Equinix Canada, Ltd. | T20: FALSE | U20: -1 | AK20: ri.mio.main.media-item.0199713b-dbcf-7ebd-9cc7-6e4ba33fe6f4_2_3 | AP20: AC Circuit - 208v - 20-amp - Three Phase - Redundant | AV20: ri.mio.main.media-item.0199713b-dbcf-7ebd-9cc7-6e4ba33fe6f4 | AW20: Quote | BD20: POW00003 | BJ20: 0 | BO20: 2 | BP20: ri.mio.main.media-item.0199713b-dbcf-7ebd-9cc7-6e4ba33fe6f4_1 | BT20: 1 | BU20: 3 | BV20: 100247283.MT1 | BX20: 44896 | CI20: 0 | CM20: FALSE | CN20: 33590
A21: QLI00020 | B21: ri.mio.main.media-item.0199713b-dbcf-7ebd-9cc7-6e4ba33fe6f4 | C21: CAD | D21: Equinix Canada, Ltd. | F21: Quote2-PO3000196864-EQUINIX-ATT+Wipro+Canada_Renewal+Post-Novation+(7+Months)__Quote_Num_1-223208968420+ATT+Sign+20230124.pdf | G21: Quote | H21: AT&T | L21: {"mimeType":"application/pdf","reference":{"type":"mediaSetViewItem","mediaSetViewItem":{"mediaSetRid":"ri.mio.main.media-set.7a7aadd5-adcf-42ac-9e71-12078d56f27e","mediaSetViewRid":"ri.mio.main.view.5660cab0-05c2-4700-94bc-c64529e38113","mediaItemRid":"ri.mio.main.media-item.0199713b-dbcf-7ebd-9cc7-6e4ba33fe6f4"}}} | N21: PO3000196864 | P21: Equinix Canada, Ltd. | T21: FALSE | U21: -1 | AK21: ri.mio.main.media-item.0199713b-dbcf-7ebd-9cc7-6e4ba33fe6f4_2_4 | AP21: AC Circuit - 208v - 20-amp - Three Phase - Redundant | AV21: ri.mio.main.media-item.0199713b-dbcf-7ebd-9cc7-6e4ba33fe6f4 | AW21: Quote | BD21: POW00003 | BJ21: 0 | BO21: 2 | BP21: ri.mio.main.media-item.0199713b-dbcf-7ebd-9cc7-6e4ba33fe6f4_1 | BT21: 1 | BU21: 4 | BV21: 100245793.MT1 | BX21: 44896 | CI21: 0 | CM21: FALSE | CN21: 33590
A22: QLI00021 | B22: ri.mio.main.media-item.0199713b-dbcf-7ebd-9cc7-6e4ba33fe6f4 | C22: CAD | D22: Equinix Canada, Ltd. | F22: Quote2-PO3000196864-EQUINIX-ATT+Wipro+Canada_Renewal+Post-Novation+(7+Months)__Quote_Num_1-223208968420+ATT+Sign+20230124.pdf | G22: Quote | H22: AT&T | L22: {"mimeType":"application/pdf","reference":{"type":"mediaSetViewItem","mediaSetViewItem":{"mediaSetRid":"ri.mio.main.media-set.7a7aadd5-adcf-42ac-9e71-12078d56f27e","mediaSetViewRid":"ri.mio.main.view.5660cab0-05c2-4700-94bc-c64529e38113","mediaItemRid":"ri.mio.main.media-item.0199713b-dbcf-7ebd-9cc7-6e4ba33fe6f4"}}} | N22: PO3000196864 | P22: Equinix Canada, Ltd. | T22: FALSE | U22: -1 | AK22: ri.mio.main.media-item.0199713b-dbcf-7ebd-9cc7-6e4ba33fe6f4_2_5 | AP22: AC Circuit - 208v - 20-amp - Three Phase - Primary | AV22: ri.mio.main.media-item.0199713b-dbcf-7ebd-9cc7-6e4ba33fe6f4 | AW22: Quote | BD22: POW00003 | BJ22: 0 | BO22: 2 | BP22: ri.mio.main.media-item.0199713b-dbcf-7ebd-9cc7-6e4ba33fe6f4_1 | BT22: 1 | BU22: 5 | BV22: 100245706.MT1 | BX22: 44896 | CI22: 0 | CM22: FALSE | CN22: 33590
A23: QLI00022 | B23: ri.mio.main.media-item.0199713b-dbcf-7ebd-9cc7-6e4ba33fe6f4 | C23: CAD | D23: Equinix Canada, Ltd. | F23: Quote2-PO3000196864-EQUINIX-ATT+Wipro+Canada_Renewal+Post-Novation+(7+Months)__Quote_Num_1-223208968420+ATT+Sign+20230124.pdf | G23: Quote | H23: AT&T | L23: {"mimeType":"application/pdf","reference":{"type":"mediaSetViewItem","mediaSetViewItem":{"mediaSetRid":"ri.mio.main.media-set.7a7aadd5-adcf-42ac-9e71-12078d56f27e","mediaSetViewRid":"ri.mio.main.view.5660cab0-05c2-4700-94bc-c64529e38113","mediaItemRid":"ri.mio.main.media-item.0199713b-dbcf-7ebd-9cc7-6e4ba33fe6f4"}}} | N23: PO3000196864 | P23: Equinix Canada, Ltd. | T23: FALSE | U23: -1 | AK23: ri.mio.main.media-item.0199713b-dbcf-7ebd-9cc7-6e4ba33fe6f4_2_6 | AP23: AC Circuit - 208v - 20-amp - Three Phase - Redundant | AV23: ri.mio.main.media-item.0199713b-dbcf-7ebd-9cc7-6e4ba33fe6f4 | AW23: Quote | BD23: POW00003 | BJ23: 0 | BO23: 2 | BP23: ri.mio.main.media-item.0199713b-dbcf-7ebd-9cc7-6e4ba33fe6f4_1 | BT23: 1 | BU23: 6 | BV23: 100247287.MT1 | BX23: 44896 | CI23: 0 | CM23: FALSE | CN23: 33590
A24: QLI00023 | B24: ri.mio.main.media-item.0199713b-dbcf-7ebd-9cc7-6e4ba33fe6f4 | C24: CAD | D24: Equinix Canada, Ltd. | F24: Quote2-PO3000196864-EQUINIX-ATT+Wipro+Canada_Renewal+Post-Novation+(7+Months)__Quote_Num_1-223208968420+ATT+Sign+20230124.pdf | G24: Quote | H24: AT&T | L24: {"mimeType":"application/pdf","reference":{"type":"mediaSetViewItem","mediaSetViewItem":{"mediaSetRid":"ri.mio.main.media-set.7a7aadd5-adcf-42ac-9e71-12078d56f27e","mediaSetViewRid":"ri.mio.main.view.5660cab0-05c2-4700-94bc-c64529e38113","mediaItemRid":"ri.mio.main.media-item.0199713b-dbcf-7ebd-9cc7-6e4ba33fe6f4"}}} | N24: PO3000196864 | P24: Equinix Canada, Ltd. | T24: FALSE | U24: -1 | AK24: ri.mio.main.media-item.0199713b-dbcf-7ebd-9cc7-6e4ba33fe6f4_2_7 | AP24: AC Circuit - 208v - 20-amp - Three Phase - Primary | AV24: ri.mio.main.media-item.0199713b-dbcf-7ebd-9cc7-6e4ba33fe6f4 | AW24: Quote | BD24: POW00003 | BJ24: 0 | BO24: 2 | BP24: ri.mio.main.media-item.0199713b-dbcf-7ebd-9cc7-6e4ba33fe6f4_1 | BT24: 1 | BU24: 7 | BV24: 100245700.MT1 | BX24: 44896 | CI24: 0 | CM24: FALSE | CN24: 33590
A25: QLI00024 | B25: ri.mio.main.media-item.0199713b-dbcf-7ebd-9cc7-6e4ba33fe6f4 | C25: CAD | D25: Equinix Canada, Ltd. | F25: Quote2-PO3000196864-EQUINIX-ATT+Wipro+Canada_Renewal+Post-Novation+(7+Months)__Quote_Num_1-223208968420+ATT+Sign+20230124.pdf | G25: Quote | H25: AT&T | L25: {"mimeType":"application/pdf","reference":{"type":"mediaSetViewItem","mediaSetViewItem":{"mediaSetRid":"ri.mio.main.media-set.7a7aadd5-adcf-42ac-9e71-12078d56f27e","mediaSetViewRid":"ri.mio.main.view.5660cab0-05c2-4700-94bc-c64529e38113","mediaItemRid":"ri.mio.main.media-item.0199713b-dbcf-7ebd-9cc7-6e4ba33fe6f4"}}} | N25: PO3000196864 | P25: Equinix Canada, Ltd. | T25: FALSE | U25: -1 | AK25: ri.mio.main.media-item.0199713b-dbcf-7ebd-9cc7-6e4ba33fe6f4_2_8 | AP25: AC Circuit - 208v - 20-amp - Three Phase - Redundant | AV25: ri.mio.main.media-item.0199713b-dbcf-7ebd-9cc7-6e4ba33fe6f4 | AW25: Quote | BD25: POW00003 | BJ25: 0 | BO25: 2 | BP25: ri.mio.main.media-item.0199713b-dbcf-7ebd-9cc7-6e4ba33fe6f4_1 | BT25: 1 | BU25: 8 | BV25: 100247281.MT1 | BX25: 44896 | CI25: 0 | CM25: FALSE | CN25: 33590
A26: QLI00025 | B26: ri.mio.main.media-item.0199713b-dbcf-7ebd-9cc7-6e4ba33fe6f4 | C26: CAD | D26: Equinix Canada, Ltd. | F26: Quote2-PO3000196864-EQUINIX-ATT+Wipro+Canada_Renewal+Post-Novation+(7+Months)__Quote_Num_1-223208968420+ATT+Sign+20230124.pdf | G26: Quote | H26: AT&T | L26: {"mimeType":"application/pdf","reference":{"type":"mediaSetViewItem","mediaSetViewItem":{"mediaSetRid":"ri.mio.main.media-set.7a7aadd5-adcf-42ac-9e71-12078d56f27e","mediaSetViewRid":"ri.mio.main.view.5660cab0-05c2-4700-94bc-c64529e38113","mediaItemRid":"ri.mio.main.media-item.0199713b-dbcf-7ebd-9cc7-6e4ba33fe6f4"}}} | N26: PO3000196864 | P26: Equinix Canada, Ltd. | T26: FALSE | U26: -1 | AK26: ri.mio.main.media-item.0199713b-dbcf-7ebd-9cc7-6e4ba33fe6f4_2_9 | AP26: AC Circuit - 208v - 20-amp - Three Phase - Primary | AV26: ri.mio.main.media-item.0199713b-dbcf-7ebd-9cc7-6e4ba33fe6f4 | AW26: Quote | BD26: POW00003 | BJ26: 0 | BO26: 2 | BP26: ri.mio.main.media-item.0199713b-dbcf-7ebd-9cc7-6e4ba33fe6f4_1 | BT26: 1 | BU26: 9 | BV26: 100245795.MT1 | BX26: 44896 | CI26: 0 | CM26: FALSE | CN26: 33590
A27: QLI00026 | B27: ri.mio.main.media-item.0199713b-dbcf-7ebd-9cc7-6e4ba33fe6f4 | C27: CAD | D27: Equinix Canada, Ltd. | F27: Quote2-PO3000196864-EQUINIX-ATT+Wipro+Canada_Renewal+Post-Novation+(7+Months)__Quote_Num_1-223208968420+ATT+Sign+20230124.pdf | G27: Quote | H27: AT&T | L27: {"mimeType":"application/pdf","reference":{"type":"mediaSetViewItem","mediaSetViewItem":{"mediaSetRid":"ri.mio.main.media-set.7a7aadd5-adcf-42ac-9e71-12078d56f27e","mediaSetViewRid":"ri.mio.main.view.5660cab0-05c2-4700-94bc-c64529e38113","mediaItemRid":"ri.mio.main.media-item.0199713b-dbcf-7ebd-9cc7-6e4ba33fe6f4"}}} | N27: PO3000196864 | P27: Equinix Canada, Ltd. | T27: FALSE | U27: -1 | AK27: ri.mio.main.media-item.0199713b-dbcf-7ebd-9cc7-6e4ba33fe6f4_6_1 | AP27: Space & Power | AV27: ri.mio.main.media-item.0199713b-dbcf-7ebd-9cc7-6e4ba33fe6f4 | AW27: Quote | BD27: 20008-LEP-005.1 | BO27: 6 | BU27: 1 | BZ27: MT1 | CA27: MT1 | CM27: FALSE | CN27: 36670
A28: QLI00027 | B28: ri.mio.main.media-item.0199713b-dbcf-7ebd-9cc7-6e4ba33fe6f4 | C28: CAD | D28: Equinix Canada, Ltd. | F28: Quote2-PO3000196864-EQUINIX-ATT+Wipro+Canada_Renewal+Post-Novation+(7+Months)__Quote_Num_1-223208968420+ATT+Sign+20230124.pdf | G28: Quote | H28: AT&T | L28: {"mimeType":"application/pdf","reference":{"type":"mediaSetViewItem","mediaSetViewItem":{"mediaSetRid":"ri.mio.main.media-set.7a7aadd5-adcf-42ac-9e71-12078d56f27e","mediaSetViewRid":"ri.mio.main.view.5660cab0-05c2-4700-94bc-c64529e38113","mediaItemRid":"ri.mio.main.media-item.0199713b-dbcf-7ebd-9cc7-6e4ba33fe6f4"}}} | N28: PO3000196864 | P28: Equinix Canada, Ltd. | T28: FALSE | U28: -1 | AK28: ri.mio.main.media-item.0199713b-dbcf-7ebd-9cc7-6e4ba33fe6f4_6_2 | AP28: Interconnection | AV28: ri.mio.main.media-item.0199713b-dbcf-7ebd-9cc7-6e4ba33fe6f4 | AW28: Quote | BD28: 20008-LEP-005.1 | BO28: 6 | BU28: 2 | BZ28: MT1 | CA28: MT1 | CM28: FALSE | CN28: 36670
A29: QLI00028 | B29: ri.mio.main.media-item.0199713b-dbcf-7ebd-9cc7-6e4ba33fe6f4 | C29: CAD | D29: Equinix Canada, Ltd. | F29: Quote2-PO3000196864-EQUINIX-ATT+Wipro+Canada_Renewal+Post-Novation+(7+Months)__Quote_Num_1-223208968420+ATT+Sign+20230124.pdf | G29: Quote | H29: AT&T | L29: {"mimeType":"application/pdf","reference":{"type":"mediaSetViewItem","mediaSetViewItem":{"mediaSetRid":"ri.mio.main.media-set.7a7aadd5-adcf-42ac-9e71-12078d56f27e","mediaSetViewRid":"ri.mio.main.view.5660cab0-05c2-4700-94bc-c64529e38113","mediaItemRid":"ri.mio.main.media-item.0199713b-dbcf-7ebd-9cc7-6e4ba33fe6f4"}}} | N29: PO3000196864 | P29: Equinix Canada, Ltd. | T29: FALSE | U29: -1 | AK29: ri.mio.main.media-item.0199713b-dbcf-7ebd-9cc7-6e4ba33fe6f4_6_3 | AP29: Services | AV29: ri.mio.main.media-item.0199713b-dbcf-7ebd-9cc7-6e4ba33fe6f4 | AW29: Quote | BO29: 6 | BU29: 3 | BZ29: MT1 | CA29: MT1 | CM29: FALSE | CN29: 36670
A30: QLI00029 | B30: ri.mio.main.media-item.0199713b-e2af-7291-b207-419560cb2e62 | C30: CAD | D30: Equinix Canada, Ltd. | F30: Quote-PO3000196864-EQUINIX-ATT+Wipro+Canada_Renewal+Post-Novation_MT1+OT1_1-222682409611+(37+months)+ATT+Signed+20230119.pdf | G30: Quote | H30: AT&T | L30: {"mimeType":"application/pdf","reference":{"type":"mediaSetViewItem","mediaSetViewItem":{"mediaSetRid":"ri.mio.main.media-set.7a7aadd5-adcf-42ac-9e71-12078d56f27e","mediaSetViewRid":"ri.mio.main.view.5660cab0-05c2-4700-94bc-c64529e38113","mediaItemRid":"ri.mio.main.media-item.0199713b-e2af-7291-b207-419560cb2e62"}}} | N30: PO3000196864 | P30: Equinix Canada, Ltd. | T30: FALSE | U30: -1 | AK30: ri.mio.main.media-item.0199713b-e2af-7291-b207-419560cb2e62_10_1 | AP30: Cabinet - 3.03 kVA - Closed Cabinet | AV30: ri.mio.main.media-item.0199713b-e2af-7291-b207-419560cb2e62 | AW30: Quote | BD30: CAB00001 | BJ30: 0 | BO30: 10 | BP30: ri.mio.main.media-item.0199713b-e2af-7291-b207-419560cb2e62_9 | BT30: 1 | BU30: 1 | BV30: 0216-00087170 | BX30: 44896 | CI30: 0 | CM30: FALSE | CN30: 45445
A31: QLI00030 | B31: ri.mio.main.media-item.0199713b-e2af-7291-b207-419560cb2e62 | C31: CAD | D31: Equinix Canada, Ltd. | F31: Quote-PO3000196864-EQUINIX-ATT+Wipro+Canada_Renewal+Post-Novation_MT1+OT1_1-222682409611+(37+months)+ATT+Signed+20230119.pdf | G31: Quote | H31: AT&T | L31: {"mimeType":"application/pdf","reference":{"type":"mediaSetViewItem","mediaSetViewItem":{"mediaSetRid":"ri.mio.main.media-set.7a7aadd5-adcf-42ac-9e71-12078d56f27e","mediaSetViewRid":"ri.mio.main.view.5660cab0-05c2-4700-94bc-c64529e38113","mediaItemRid":"ri.mio.main.media-item.0199713b-e2af-7291-b207-419560cb2e62"}}} | N31: PO3000196864 | P31: Equinix Canada, Ltd. | T31: FALSE | U31: -1 | AK31: ri.mio.main.media-item.0199713b-e2af-7291-b207-419560cb2e62_10_10 | AP31: Cabinet - 3.03 kVA - Closed Cabinet | AV31: ri.mio.main.media-item.0199713b-e2af-7291-b207-419560cb2e62 | AW31: Quote | BD31: CAB00001 | BJ31: 0 | BO31: 10 | BP31: ri.mio.main.media-item.0199713b-e2af-7291-b207-419560cb2e62_9 | BT31: 1 | BU31: 10 | BV31: 0225-00087179 | BX31: 44896 | CI31: 0 | CM31: FALSE | CN31: 45445
A32: QLI00031 | B32: ri.mio.main.media-item.0199713b-e2af-7291-b207-419560cb2e62 | C32: CAD | D32: Equinix Canada, Ltd. | F32: Quote-PO3000196864-EQUINIX-ATT+Wipro+Canada_Renewal+Post-Novation_MT1+OT1_1-222682409611+(37+months)+ATT+Signed+20230119.pdf | G32: Quote | H32: AT&T | L32: {"mimeType":"application/pdf","reference":{"type":"mediaSetViewItem","mediaSetViewItem":{"mediaSetRid":"ri.mio.main.media-set.7a7aadd5-adcf-42ac-9e71-12078d56f27e","mediaSetViewRid":"ri.mio.main.view.5660cab0-05c2-4700-94bc-c64529e38113","mediaItemRid":"ri.mio.main.media-item.0199713b-e2af-7291-b207-419560cb2e62"}}} | N32: PO3000196864 | P32: Equinix Canada, Ltd. | T32: FALSE | U32: -1 | AK32: ri.mio.main.media-item.0199713b-e2af-7291-b207-419560cb2e62_10_11 | AP32: Cabinet - 3.03 kVA - Closed Cabinet | AV32: ri.mio.main.media-item.0199713b-e2af-7291-b207-419560cb2e62 | AW32: Quote | BD32: CAB00001 | BJ32: 0 | BO32: 10 | BP32: ri.mio.main.media-item.0199713b-e2af-7291-b207-419560cb2e62_9 | BT32: 1 | BU32: 11 | BV32: 0226-00087180 | BX32: 44896 | CI32: 0 | CM32: FALSE | CN32: 45445
A33: QLI00032 | B33: ri.mio.main.media-item.0199713b-e2af-7291-b207-419560cb2e62 | C33: CAD | D33: Equinix Canada, Ltd. | F33: Quote-PO3000196864-EQUINIX-ATT+Wipro+Canada_Renewal+Post-Novation_MT1+OT1_1-222682409611+(37+months)+ATT+Signed+20230119.pdf | G33: Quote | H33: AT&T | L33: {"mimeType":"application/pdf","reference":{"type":"mediaSetViewItem","mediaSetViewItem":{"mediaSetRid":"ri.mio.main.media-set.7a7aadd5-adcf-42ac-9e71-12078d56f27e","mediaSetViewRid":"ri.mio.main.view.5660cab0-05c2-4700-94bc-c64529e38113","mediaItemRid":"ri.mio.main.media-item.0199713b-e2af-7291-b207-419560cb2e62"}}} | N33: PO3000196864 | P33: Equinix Canada, Ltd. | T33: FALSE | U33: -1 | AK33: ri.mio.main.media-item.0199713b-e2af-7291-b207-419560cb2e62_10_12 | AP33: Cage - Customer Provided Cabinet - 48 Cabinets - 182 KVA | AV33: ri.mio.main.media-item.0199713b-e2af-7291-b207-419560cb2e62 | AW33: Quote | BD33: CAG00001 | BJ33: 61425 | BO33: 10 | BP33: ri.mio.main.media-item.0199713b-e2af-7291-b207-419560cb2e62_9 | BT33: 182 | BU33: 12 | BV33: 113995-00078068 | BX33: 44896 | CI33: 61425 | CM33: FALSE | CN33: 45445
A34: QLI00033 | B34: ri.mio.main.media-item.0199713b-e2af-7291-b207-419560cb2e62 | C34: CAD | D34: Equinix Canada, Ltd. | F34: Quote-PO3000196864-EQUINIX-ATT+Wipro+Canada_Renewal+Post-Novation_MT1+OT1_1-222682409611+(37+months)+ATT+Signed+20230119.pdf | G34: Quote | H34: AT&T | L34: {"mimeType":"application/pdf","reference":{"type":"mediaSetViewItem","mediaSetViewItem":{"mediaSetRid":"ri.mio.main.media-set.7a7aadd5-adcf-42ac-9e71-12078d56f27e","mediaSetViewRid":"ri.mio.main.view.5660cab0-05c2-4700-94bc-c64529e38113","mediaItemRid":"ri.mio.main.media-item.0199713b-e2af-7291-b207-419560cb2e62"}}} | N34: PO3000196864 | P34: Equinix Canada, Ltd. | T34: FALSE | U34: -1 | AK34: ri.mio.main.media-item.0199713b-e2af-7291-b207-419560cb2e62_10_13 | AP34: AC Power | AV34: ri.mio.main.media-item.0199713b-e2af-7291-b207-419560cb2e62 | AW34: Quote | BD34: POW00003 | BJ34: 61425 | BO34: 10 | BP34: ri.mio.main.media-item.0199713b-e2af-7291-b207-419560cb2e62_9 | BT34: 182 | BU34: 13 | BV34: 7-10000022957 | BX34: 44896 | CI34: 61425 | CM34: FALSE | CN34: 45445
A35: QLI00034 | B35: ri.mio.main.media-item.0199713b-e2af-7291-b207-419560cb2e62 | C35: CAD | D35: Equinix Canada, Ltd. | F35: Quote-PO3000196864-EQUINIX-ATT+Wipro+Canada_Renewal+Post-Novation_MT1+OT1_1-222682409611+(37+months)+ATT+Signed+20230119.pdf | G35: Quote | H35: AT&T | L35: {"mimeType":"application/pdf","reference":{"type":"mediaSetViewItem","mediaSetViewItem":{"mediaSetRid":"ri.mio.main.media-set.7a7aadd5-adcf-42ac-9e71-12078d56f27e","mediaSetViewRid":"ri.mio.main.view.5660cab0-05c2-4700-94bc-c64529e38113","mediaItemRid":"ri.mio.main.media-item.0199713b-e2af-7291-b207-419560cb2e62"}}} | N35: PO3000196864 | P35: Equinix Canada, Ltd. | T35: FALSE | U35: -1 | AK35: ri.mio.main.media-item.0199713b-e2af-7291-b207-419560cb2e62_10_14 | AP35: AC Circuit - 230v - 30-amp - Single Phase - Primary | AV35: ri.mio.main.media-item.0199713b-e2af-7291-b207-419560cb2e62 | AW35: Quote | BD35: POW00003 | BJ35: 0 | BO35: 10 | BP35: ri.mio.main.media-item.0199713b-e2af-7291-b207-419560cb2e62_9 | BT35: 1 | BU35: 14 | BV35: 100088053.OT1 | BX35: 44896 | CI35: 0 | CM35: FALSE | CN35: 45445
A36: QLI00035 | B36: ri.mio.main.media-item.0199713b-e2af-7291-b207-419560cb2e62 | C36: CAD | D36: Equinix Canada, Ltd. | F36: Quote-PO3000196864-EQUINIX-ATT+Wipro+Canada_Renewal+Post-Novation_MT1+OT1_1-222682409611+(37+months)+ATT+Signed+20230119.pdf | G36: Quote | H36: AT&T | L36: {"mimeType":"application/pdf","reference":{"type":"mediaSetViewItem","mediaSetViewItem":{"mediaSetRid":"ri.mio.main.media-set.7a7aadd5-adcf-42ac-9e71-12078d56f27e","mediaSetViewRid":"ri.mio.main.view.5660cab0-05c2-4700-94bc-c64529e38113","mediaItemRid":"ri.mio.main.media-item.0199713b-e2af-7291-b207-419560cb2e62"}}} | N36: PO3000196864 | P36: Equinix Canada, Ltd. | T36: FALSE | U36: -1 | AK36: ri.mio.main.media-item.0199713b-e2af-7291-b207-419560cb2e62_10_15 | AP36: AC Circuit - 230v - 30-amp - Single Phase - Redundant | AV36: ri.mio.main.media-item.0199713b-e2af-7291-b207-419560cb2e62 | AW36: Quote | BD36: POW00003 | BJ36: 0 | BO36: 10 | BP36: ri.mio.main.media-item.0199713b-e2af-7291-b207-419560cb2e62_9 | BT36: 1 | BU36: 15 | BV36: 100088054.OT1 | BX36: 44896 | CI36: 0 | CM36: FALSE | CN36: 45445
A37: QLI00036 | B37: ri.mio.main.media-item.0199713b-e2af-7291-b207-419560cb2e62 | C37: CAD | D37: Equinix Canada, Ltd. | F37: Quote-PO3000196864-EQUINIX-ATT+Wipro+Canada_Renewal+Post-Novation_MT1+OT1_1-222682409611+(37+months)+ATT+Signed+20230119.pdf | G37: Quote | H37: AT&T | L37: {"mimeType":"application/pdf","reference":{"type":"mediaSetViewItem","mediaSetViewItem":{"mediaSetRid":"ri.mio.main.media-set.7a7aadd5-adcf-42ac-9e71-12078d56f27e","mediaSetViewRid":"ri.mio.main.view.5660cab0-05c2-4700-94bc-c64529e38113","mediaItemRid":"ri.mio.main.media-item.0199713b-e2af-7291-b207-419560cb2e62"}}} | N37: PO3000196864 | P37: Equinix Canada, Ltd. | T37: FALSE | U37: -1 | AK37: ri.mio.main.media-item.0199713b-e2af-7291-b207-419560cb2e62_10_16 | AP37: AC Circuit - 230v - 30-amp - Single Phase - Primary | AV37: ri.mio.main.media-item.0199713b-e2af-7291-b207-419560cb2e62 | AW37: Quote | BD37: POW00003 | BJ37: 0 | BO37: 10 | BP37: ri.mio.main.media-item.0199713b-e2af-7291-b207-419560cb2e62_9 | BT37: 1 | BU37: 16 | BV37: 100088057.OT1 | BX37: 44896 | CI37: 0 | CM37: FALSE | CN37: 45445
A38: QLI00037 | B38: ri.mio.main.media-item.0199713b-e2af-7291-b207-419560cb2e62 | C38: CAD | D38: Equinix Canada, Ltd. | F38: Quote-PO3000196864-EQUINIX-ATT+Wipro+Canada_Renewal+Post-Novation_MT1+OT1_1-222682409611+(37+months)+ATT+Signed+20230119.pdf | G38: Quote | H38: AT&T | L38: {"mimeType":"application/pdf","reference":{"type":"mediaSetViewItem","mediaSetViewItem":{"mediaSetRid":"ri.mio.main.media-set.7a7aadd5-adcf-42ac-9e71-12078d56f27e","mediaSetViewRid":"ri.mio.main.view.5660cab0-05c2-4700-94bc-c64529e38113","mediaItemRid":"ri.mio.main.media-item.0199713b-e2af-7291-b207-419560cb2e62"}}} | N38: PO3000196864 | P38: Equinix Canada, Ltd. | T38: FALSE | U38: -1 | AK38: ri.mio.main.media-item.0199713b-e2af-7291-b207-419560cb2e62_10_17 | AP38: AC Circuit - 230v - 30-amp - Single Phase - Redundant | AV38: ri.mio.main.media-item.0199713b-e2af-7291-b207-419560cb2e62 | AW38: Quote | BD38: POW00003 | BJ38: 0 | BO38: 10 | BP38: ri.mio.main.media-item.0199713b-e2af-7291-b207-419560cb2e62_9 | BT38: 1 | BU38: 17 | BV38: 100088058.OT1 | BX38: 44896 | CI38: 0 | CM38: FALSE | CN38: 45445
A39: QLI00038 | B39: ri.mio.main.media-item.0199713b-e2af-7291-b207-419560cb2e62 | C39: CAD | D39: Equinix Canada, Ltd. | F39: Quote-PO3000196864-EQUINIX-ATT+Wipro+Canada_Renewal+Post-Novation_MT1+OT1_1-222682409611+(37+months)+ATT+Signed+20230119.pdf | G39: Quote | H39: AT&T | L39: {"mimeType":"application/pdf","reference":{"type":"mediaSetViewItem","mediaSetViewItem":{"mediaSetRid":"ri.mio.main.media-set.7a7aadd5-adcf-42ac-9e71-12078d56f27e","mediaSetViewRid":"ri.mio.main.view.5660cab0-05c2-4700-94bc-c64529e38113","mediaItemRid":"ri.mio.main.media-item.0199713b-e2af-7291-b207-419560cb2e62"}}} | N39: PO3000196864 | P39: Equinix Canada, Ltd. | T39: FALSE | U39: -1 | AK39: ri.mio.main.media-item.0199713b-e2af-7291-b207-419560cb2e62_10_18 | AP39: AC Circuit - 230v - 30-amp - Single Phase - Primary | AV39: ri.mio.main.media-item.0199713b-e2af-7291-b207-419560cb2e62 | AW39: Quote | BD39: POW00003 | BJ39: 0 | BO39: 10 | BP39: ri.mio.main.media-item.0199713b-e2af-7291-b207-419560cb2e62_9 | BT39: 1 | BU39: 18 | BV39: 100088059.OT1 | BX39: 44896 | CI39: 0 | CM39: FALSE | CN39: 45445
A40: QLI00039 | B40: ri.mio.main.media-item.0199713b-e2af-7291-b207-419560cb2e62 | C40: CAD | D40: Equinix Canada, Ltd. | F40: Quote-PO3000196864-EQUINIX-ATT+Wipro+Canada_Renewal+Post-Novation_MT1+OT1_1-222682409611+(37+months)+ATT+Signed+20230119.pdf | G40: Quote | H40: AT&T | L40: {"mimeType":"application/pdf","reference":{"type":"mediaSetViewItem","mediaSetViewItem":{"mediaSetRid":"ri.mio.main.media-set.7a7aadd5-adcf-42ac-9e71-12078d56f27e","mediaSetViewRid":"ri.mio.main.view.5660cab0-05c2-4700-94bc-c64529e38113","mediaItemRid":"ri.mio.main.media-item.0199713b-e2af-7291-b207-419560cb2e62"}}} | N40: PO3000196864 | P40: Equinix Canada, Ltd. | T40: FALSE | U40: -1 | AK40: ri.mio.main.media-item.0199713b-e2af-7291-b207-419560cb2e62_10_19 | AP40: AC Circuit - 230v - 30-amp - Single Phase - Redundant | AV40: ri.mio.main.media-item.0199713b-e2af-7291-b207-419560cb2e62 | AW40: Quote | BD40: POW00003 | BJ40: 0 | BO40: 10 | BP40: ri.mio.main.media-item.0199713b-e2af-7291-b207-419560cb2e62_9 | BT40: 1 | BU40: 19 | BV40: 100088060.OT1 | BX40: 44896 | CI40: 0 | CM40: FALSE | CN40: 45445
A41: QLI00040 | B41: ri.mio.main.media-item.0199713b-e2af-7291-b207-419560cb2e62 | C41: CAD | D41: Equinix Canada, Ltd. | F41: Quote-PO3000196864-EQUINIX-ATT+Wipro+Canada_Renewal+Post-Novation_MT1+OT1_1-222682409611+(37+months)+ATT+Signed+20230119.pdf | G41: Quote | H41: AT&T | L41: {"mimeType":"application/pdf","reference":{"type":"mediaSetViewItem","mediaSetViewItem":{"mediaSetRid":"ri.mio.main.media-set.7a7aadd5-adcf-42ac-9e71-12078d56f27e","mediaSetViewRid":"ri.mio.main.view.5660cab0-05c2-4700-94bc-c64529e38113","mediaItemRid":"ri.mio.main.media-item.0199713b-e2af-7291-b207-419560cb2e62"}}} | N41: PO3000196864 | P41: Equinix Canada, Ltd. | T41: FALSE | U41: -1 | AK41: ri.mio.main.media-item.0199713b-e2af-7291-b207-419560cb2e62_10_2 | AP41: Cabinet - 3.03 kVA - Closed Cabinet | AV41: ri.mio.main.media-item.0199713b-e2af-7291-b207-419560cb2e62 | AW41: Quote | BD41: CAB00001 | BJ41: 0 | BO41: 10 | BP41: ri.mio.main.media-item.0199713b-e2af-7291-b207-419560cb2e62_9 | BT41: 1 | BU41: 2 | BV41: 0217-00087171 | BX41: 44896 | CI41: 0 | CM41: FALSE | CN41: 45445
... A88: QLI00087 | B88: ri.mio.main.media-item.0199713b-e2af-7291-b207-419560cb2e62 | C88: CAD | D88: Equinix Canada, Ltd. | F88: Quote-PO3000196864-EQUINIX-ATT+Wipro+Canada_Renewal+Post-Novation_MT1+OT1_1-222682409611+(37+months)+ATT+Signed+20230119.pdf | G88: Quote | H88: AT&T | L88: {"mimeType":"application/pdf","reference":{"type":"mediaSetViewItem","mediaSetViewItem":{"mediaSetRid":"ri.mio.main.media-set.7a7aadd5-adcf-42ac-9e71-12078d56f27e","mediaSetViewRid":"ri.mio.main.view.5660cab0-05c2-4700-94bc-c64529e38113","mediaItemRid":"ri.mio.main.media-item.0199713b-e2af-7291-b207-419560cb2e62"}}} | N88: PO3000196864 | P88: Equinix Canada, Ltd. | T88: FALSE | U88: -1 | AK88: ri.mio.main.media-item.0199713b-e2af-7291-b207-419560cb2e62_11_9 | AP88: AC Circuit - 230v - 30-amp - Three Phase - Redundant | AV88: ri.mio.main.media-item.0199713b-e2af-7291-b207-419560cb2e62 | AW88: Quote | BD88: POW00003 | BJ88: 0 | BO88: 11 | BP88: ri.mio.main.media-item.0199713b-e2af-7291-b207-419560cb2e62_10 | BT88: 1 | BU88: 9 | BV88: 100088080.OT1 | BX88: 44896 | CI88: 0 | CM88: FALSE | CN88: 42635
A89: QLI00088 | B89: ri.mio.main.media-item.0199713b-e2af-7291-b207-419560cb2e62 | C89: CAD | D89: Equinix Canada, Ltd. | F89: Quote-PO3000196864-EQUINIX-ATT+Wipro+Canada_Renewal+Post-Novation_MT1+OT1_1-222682409611+(37+months)+ATT+Signed+20230119.pdf | G89: Quote | H89: AT&T | L89: {"mimeType":"application/pdf","reference":{"type":"mediaSetViewItem","mediaSetViewItem":{"mediaSetRid":"ri.mio.main.media-set.7a7aadd5-adcf-42ac-9e71-12078d56f27e","mediaSetViewRid":"ri.mio.main.view.5660cab0-05c2-4700-94bc-c64529e38113","mediaItemRid":"ri.mio.main.media-item.0199713b-e2af-7291-b207-419560cb2e62"}}} | N89: PO3000196864 | P89: Equinix Canada, Ltd. | T89: FALSE | U89: -1 | AK89: ri.mio.main.media-item.0199713b-e2af-7291-b207-419560cb2e62_12_1 | AP89: AC Circuit - 230v - 20-amp - Three Phase - Redundant | AV89: ri.mio.main.media-item.0199713b-e2af-7291-b207-419560cb2e62 | AW89: Quote | BD89: POW00003 | BJ89: 0 | BL89: - | BO89: 12 | BP89: ri.mio.main.media-item.0199713b-e2af-7291-b207-419560cb2e62_11 | BT89: 1 | BU89: 1 | BV89: 100088116.OT1 | BX89: 44896 | BZ89: OT1 | CA89: OT1 | CM89: FALSE | CN89: 44030
A90: QLI00089 | B90: ri.mio.main.media-item.0199713b-e2af-7291-b207-419560cb2e62 | C90: CAD | D90: Equinix Canada, Ltd. | F90: Quote-PO3000196864-EQUINIX-ATT+Wipro+Canada_Renewal+Post-Novation_MT1+OT1_1-222682409611+(37+months)+ATT+Signed+20230119.pdf | G90: Quote | H90: AT&T | L90: {"mimeType":"application/pdf","reference":{"type":"mediaSetViewItem","mediaSetViewItem":{"mediaSetRid":"ri.mio.main.media-set.7a7aadd5-adcf-42ac-9e71-12078d56f27e","mediaSetViewRid":"ri.mio.main.view.5660cab0-05c2-4700-94bc-c64529e38113","mediaItemRid":"ri.mio.main.media-item.0199713b-e2af-7291-b207-419560cb2e62"}}} | N90: PO3000196864 | P90: Equinix Canada, Ltd. | T90: FALSE | U90: -1 | AK90: ri.mio.main.media-item.0199713b-e2af-7291-b207-419560cb2e62_12_10 | AP90: AC Circuit - 230v - 30-amp - Three Phase - Primary | AV90: ri.mio.main.media-item.0199713b-e2af-7291-b207-419560cb2e62 | AW90: Quote | BD90: POW00003 | BJ90: 0 | BL90: - | BO90: 12 | BP90: ri.mio.main.media-item.0199713b-e2af-7291-b207-419560cb2e62_11 | BT90: 1 | BU90: 10 | BV90: 100088125.OT1 | BX90: 44896 | BZ90: OT1 | CA90: OT1 | CM90: FALSE | CN90: 44030
A91: QLI00090 | B91: ri.mio.main.media-item.0199713b-e2af-7291-b207-419560cb2e62 | C91: CAD | D91: Equinix Canada, Ltd. | F91: Quote-PO3000196864-EQUINIX-ATT+Wipro+Canada_Renewal+Post-Novation_MT1+OT1_1-222682409611+(37+months)+ATT+Signed+20230119.pdf | G91: Quote | H91: AT&T | L91: {"mimeType":"application/pdf","reference":{"type":"mediaSetViewItem","mediaSetViewItem":{"mediaSetRid":"ri.mio.main.media-set.7a7aadd5-adcf-42ac-9e71-12078d56f27e","mediaSetViewRid":"ri.mio.main.view.5660cab0-05c2-4700-94bc-c64529e38113","mediaItemRid":"ri.mio.main.media-item.0199713b-e2af-7291-b207-419560cb2e62"}}} | N91: PO3000196864 | P91: Equinix Canada, Ltd. | T91: FALSE | U91: -1 | AK91: ri.mio.main.media-item.0199713b-e2af-7291-b207-419560cb2e62_12_11 | AP91: AC Circuit - 230v - 30-amp - Three Phase - Redundant | AV91: ri.mio.main.media-item.0199713b-e2af-7291-b207-419560cb2e62 | AW91: Quote | BD91: POW00003 | BJ91: 0 | BL91: - | BO91: 12 | BP91: ri.mio.main.media-item.0199713b-e2af-7291-b207-419560cb2e62_11 | BT91: 1 | BU91: 11 | BV91: 100088126.OT1 | BX91: 44896 | BZ91: OT1 | CA91: OT1 | CM91: FALSE | CN91: 44030
A92: QLI00091 | B92: ri.mio.main.media-item.0199713b-e2af-7291-b207-419560cb2e62 | C92: CAD | D92: Equinix Canada, Ltd. | F92: Quote-PO3000196864-EQUINIX-ATT+Wipro+Canada_Renewal+Post-Novation_MT1+OT1_1-222682409611+(37+months)+ATT+Signed+20230119.pdf | G92: Quote | H92: AT&T | L92: {"mimeType":"application/pdf","reference":{"type":"mediaSetViewItem","mediaSetViewItem":{"mediaSetRid":"ri.mio.main.media-set.7a7aadd5-adcf-42ac-9e71-12078d56f27e","mediaSetViewRid":"ri.mio.main.view.5660cab0-05c2-4700-94bc-c64529e38113","mediaItemRid":"ri.mio.main.media-item.0199713b-e2af-7291-b207-419560cb2e62"}}} | N92: PO3000196864 | P92: Equinix Canada, Ltd. | T92: FALSE | U92: -1 | AK92: ri.mio.main.media-item.0199713b-e2af-7291-b207-419560cb2e62_12_12 | AP92: AC Circuit - 230v - 30-amp - Three Phase - Primary | AV92: ri.mio.main.media-item.0199713b-e2af-7291-b207-419560cb2e62 | AW92: Quote | BD92: POW00003 | BJ92: 0 | BL92: - | BO92: 12 | BP92: ri.mio.main.media-item.0199713b-e2af-7291-b207-419560cb2e62_11 | BT92: 1 | BU92: 12 | BV92: 100088127.OT1 | BX92: 44896 | BZ92: OT1 | CA92: OT1 | CM92: FALSE | CN92: 44030
A93: QLI00092 | B93: ri.mio.main.media-item.0199713b-e2af-7291-b207-419560cb2e62 | C93: CAD | D93: Equinix Canada, Ltd. | F93: Quote-PO3000196864-EQUINIX-ATT+Wipro+Canada_Renewal+Post-Novation_MT1+OT1_1-222682409611+(37+months)+ATT+Signed+20230119.pdf | G93: Quote | H93: AT&T | L93: {"mimeType":"application/pdf","reference":{"type":"mediaSetViewItem","mediaSetViewItem":{"mediaSetRid":"ri.mio.main.media-set.7a7aadd5-adcf-42ac-9e71-12078d56f27e","mediaSetViewRid":"ri.mio.main.view.5660cab0-05c2-4700-94bc-c64529e38113","mediaItemRid":"ri.mio.main.media-item.0199713b-e2af-7291-b207-419560cb2e62"}}} | N93: PO3000196864 | P93: Equinix Canada, Ltd. | T93: FALSE | U93: -1 | AK93: ri.mio.main.media-item.0199713b-e2af-7291-b207-419560cb2e62_12_13 | AP93: AC Circuit - 230v - 30-amp - Three Phase - Redundant | AV93: ri.mio.main.media-item.0199713b-e2af-7291-b207-419560cb2e62 | AW93: Quote | BD93: POW00003 | BJ93: 0 | BL93: - | BO93: 12 | BP93: ri.mio.main.media-item.0199713b-e2af-7291-b207-419560cb2e62_11 | BT93: 1 | BU93: 13 | BV93: 100088128.OT1 | BX93: 44896 | BZ93: OT1 | CA93: OT1 | CM93: FALSE | CN93: 44030
A94: QLI00093 | B94: ri.mio.main.media-item.0199713b-e2af-7291-b207-419560cb2e62 | C94: CAD | D94: Equinix Canada, Ltd. | F94: Quote-PO3000196864-EQUINIX-ATT+Wipro+Canada_Renewal+Post-Novation_MT1+OT1_1-222682409611+(37+months)+ATT+Signed+20230119.pdf | G94: Quote | H94: AT&T | L94: {"mimeType":"application/pdf","reference":{"type":"mediaSetViewItem","mediaSetViewItem":{"mediaSetRid":"ri.mio.main.media-set.7a7aadd5-adcf-42ac-9e71-12078d56f27e","mediaSetViewRid":"ri.mio.main.view.5660cab0-05c2-4700-94bc-c64529e38113","mediaItemRid":"ri.mio.main.media-item.0199713b-e2af-7291-b207-419560cb2e62"}}} | N94: PO3000196864 | P94: Equinix Canada, Ltd. | T94: FALSE | U94: -1 | AK94: ri.mio.main.media-item.0199713b-e2af-7291-b207-419560cb2e62_12_14 | AP94: AC Circuit - 230v - 20-amp - Three Phase - Redundant | AV94: ri.mio.main.media-item.0199713b-e2af-7291-b207-419560cb2e62 | AW94: Quote | BD94: POW00003 | BJ94: 0 | BL94: - | BO94: 12 | BP94: ri.mio.main.media-item.0199713b-e2af-7291-b207-419560cb2e62_11 | BT94: 1 | BU94: 14 | BV94: 100088129.OT1 | BX94: 44896 | BZ94: OT1 | CA94: OT1 | CM94: FALSE | CN94: 44030
A95: QLI00094 | B95: ri.mio.main.media-item.0199713b-e2af-7291-b207-419560cb2e62 | C95: CAD | D95: Equinix Canada, Ltd. | F95: Quote-PO3000196864-EQUINIX-ATT+Wipro+Canada_Renewal+Post-Novation_MT1+OT1_1-222682409611+(37+months)+ATT+Signed+20230119.pdf | G95: Quote | H95: AT&T | L95: {"mimeType":"application/pdf","reference":{"type":"mediaSetViewItem","mediaSetViewItem":{"mediaSetRid":"ri.mio.main.media-set.7a7aadd5-adcf-42ac-9e71-12078d56f27e","mediaSetViewRid":"ri.mio.main.view.5660cab0-05c2-4700-94bc-c64529e38113","mediaItemRid":"ri.mio.main.media-item.0199713b-e2af-7291-b207-419560cb2e62"}}} | N95: PO3000196864 | P95: Equinix Canada, Ltd. | T95: FALSE | U95: -1 | AK95: ri.mio.main.media-item.0199713b-e2af-7291-b207-419560cb2e62_12_15 | AP95: AC Circuit - 230v - 30-amp - Three Phase - Primary | AV95: ri.mio.main.media-item.0199713b-e2af-7291-b207-419560cb2e62 | AW95: Quote | BD95: POW00003 | BJ95: 0 | BL95: - | BO95: 12 | BP95: ri.mio.main.media-item.0199713b-e2af-7291-b207-419560cb2e62_11 | BT95: 1 | BU95: 15 | BV95: 100088130.OT1 | BX95: 44896 | BZ95: OT1 | CA95: OT1 | CM95: FALSE | CN95: 44030
A96: QLI00095 | B96: ri.mio.main.media-item.0199713b-e2af-7291-b207-419560cb2e62 | C96: CAD | D96: Equinix Canada, Ltd. | F96: Quote-PO3000196864-EQUINIX-ATT+Wipro+Canada_Renewal+Post-Novation_MT1+OT1_1-222682409611+(37+months)+ATT+Signed+20230119.pdf | G96: Quote | H96: AT&T | L96: {"mimeType":"application/pdf","reference":{"type":"mediaSetViewItem","mediaSetViewItem":{"mediaSetRid":"ri.mio.main.media-set.7a7aadd5-adcf-42ac-9e71-12078d56f27e","mediaSetViewRid":"ri.mio.main.view.5660cab0-05c2-4700-94bc-c64529e38113","mediaItemRid":"ri.mio.main.media-item.0199713b-e2af-7291-b207-419560cb2e62"}}} | N96: PO3000196864 | P96: Equinix Canada, Ltd. | T96: FALSE | U96: -1 | AK96: ri.mio.main.media-item.0199713b-e2af-7291-b207-419560cb2e62_12_16 | AP96: AC Circuit - 230v - 30-amp - Three Phase - Redundant | AV96: ri.mio.main.media-item.0199713b-e2af-7291-b207-419560cb2e62 | AW96: Quote | BD96: POW00003 | BJ96: 0 | BL96: - | BO96: 12 | BP96: ri.mio.main.media-item.0199713b-e2af-7291-b207-419560cb2e62_11 | BT96: 1 | BU96: 16 | BV96: 100088131.OT1 | BX96: 44896 | BZ96: OT1 | CA96: OT1 | CM96: FALSE | CN96: 44030
A97: QLI00096 | B97: ri.mio.main.media-item.0199713b-e2af-7291-b207-419560cb2e62 | C97: CAD | D97: Equinix Canada, Ltd. | F97: Quote-PO3000196864-EQUINIX-ATT+Wipro+Canada_Renewal+Post-Novation_MT1+OT1_1-222682409611+(37+months)+ATT+Signed+20230119.pdf | G97: Quote | H97: AT&T | L97: {"mimeType":"application/pdf","reference":{"type":"mediaSetViewItem","mediaSetViewItem":{"mediaSetRid":"ri.mio.main.media-set.7a7aadd5-adcf-42ac-9e71-12078d56f27e","mediaSetViewRid":"ri.mio.main.view.5660cab0-05c2-4700-94bc-c64529e38113","mediaItemRid":"ri.mio.main.media-item.0199713b-e2af-7291-b207-419560cb2e62"}}} | N97: PO3000196864 | P97: Equinix Canada, Ltd. | T97: FALSE | U97: -1 | AK97: ri.mio.main.media-item.0199713b-e2af-7291-b207-419560cb2e62_12_17 | AP97: AC Circuit - 230v - 30-amp - Three Phase - Primary | AV97: ri.mio.main.media-item.0199713b-e2af-7291-b207-419560cb2e62 | AW97: Quote | BD97: POW00003 | BJ97: 0 | BL97: - | BO97: 12 | BP97: ri.mio.main.media-item.0199713b-e2af-7291-b207-419560cb2e62_11 | BT97: 1 | BU97: 17 | BV97: 100088132.OT1 | BX97: 44896 | BZ97: OT1 | CA97: OT1 | CM97: FALSE | CN97: 44030
A98: QLI00097 | B98: ri.mio.main.media-item.0199713b-e2af-7291-b207-419560cb2e62 | C98: CAD | D98: Equinix Canada, Ltd. | F98: Quote-PO3000196864-EQUINIX-ATT+Wipro+Canada_Renewal+Post-Novation_MT1+OT1_1-222682409611+(37+months)+ATT+Signed+20230119.pdf | G98: Quote | H98: AT&T | L98: {"mimeType":"application/pdf","reference":{"type":"mediaSetViewItem","mediaSetViewItem":{"mediaSetRid":"ri.mio.main.media-set.7a7aadd5-adcf-42ac-9e71-12078d56f27e","mediaSetViewRid":"ri.mio.main.view.5660cab0-05c2-4700-94bc-c64529e38113","mediaItemRid":"ri.mio.main.media-item.0199713b-e2af-7291-b207-419560cb2e62"}}} | N98: PO3000196864 | P98: Equinix Canada, Ltd. | T98: FALSE | U98: -1 | AK98: ri.mio.main.media-item.0199713b-e2af-7291-b207-419560cb2e62_12_18 | AP98: AC Circuit - 230v - 30-amp - Three Phase - Redundant | AV98: ri.mio.main.media-item.0199713b-e2af-7291-b207-419560cb2e62 | AW98: Quote | BD98: POW00003 | BJ98: 0 | BL98: - | BO98: 12 | BP98: ri.mio.main.media-item.0199713b-e2af-7291-b207-419560cb2e62_11 | BT98: 1 | BU98: 18 | BV98: 100088133.OT1 | BX98: 44896 | BZ98: OT1 | CA98: OT1 | CM98: FALSE | CN98: 44030
A99: QLI00098 | B99: ri.mio.main.media-item.0199713b-e2af-7291-b207-419560cb2e62 | C99: CAD | D99: Equinix Canada, Ltd. | F99: Quote-PO3000196864-EQUINIX-ATT+Wipro+Canada_Renewal+Post-Novation_MT1+OT1_1-222682409611+(37+months)+ATT+Signed+20230119.pdf | G99: Quote | H99: AT&T | L99: {"mimeType":"application/pdf","reference":{"type":"mediaSetViewItem","mediaSetViewItem":{"mediaSetRid":"ri.mio.main.media-set.7a7aadd5-adcf-42ac-9e71-12078d56f27e","mediaSetViewRid":"ri.mio.main.view.5660cab0-05c2-4700-94bc-c64529e38113","mediaItemRid":"ri.mio.main.media-item.0199713b-e2af-7291-b207-419560cb2e62"}}} | N99: PO3000196864 | P99: Equinix Canada, Ltd. | T99: FALSE | U99: -1 | AK99: ri.mio.main.media-item.0199713b-e2af-7291-b207-419560cb2e62_12_19 | AP99: AC Circuit - 230v - 30-amp - Three Phase - Primary | AV99: ri.mio.main.media-item.0199713b-e2af-7291-b207-419560cb2e62 | AW99: Quote | BD99: POW00003 | BJ99: 0 | BL99: - | BO99: 12 | BP99: ri.mio.main.media-item.0199713b-e2af-7291-b207-419560cb2e62_11 | BT99: 1 | BU99: 19 | BV99: 100088134.OT1 | BX99: 44896 | BZ99: OT1 | CA99: OT1 | CM99: FALSE | CN99: 44030
A100: QLI00099 | B100: ri.mio.main.media-item.0199713b-e2af-7291-b207-419560cb2e62 | C100: CAD | D100: Equinix Canada, Ltd. | F100: Quote-PO3000196864-EQUINIX-ATT+Wipro+Canada_Renewal+Post-Novation_MT1+OT1_1-222682409611+(37+months)+ATT+Signed+20230119.pdf | G100: Quote | H100: AT&T | L100: {"mimeType":"application/pdf","reference":{"type":"mediaSetViewItem","mediaSetViewItem":{"mediaSetRid":"ri.mio.main.media-set.7a7aadd5-adcf-42ac-9e71-12078d56f27e","mediaSetViewRid":"ri.mio.main.view.5660cab0-05c2-4700-94bc-c64529e38113","mediaItemRid":"ri.mio.main.media-item.0199713b-e2af-7291-b207-419560cb2e62"}}} | N100: PO3000196864 | P100: Equinix Canada, Ltd. | T100: FALSE | U100: -1 | AK100: ri.mio.main.media-item.0199713b-e2af-7291-b207-419560cb2e62_12_2 | AP100: AC Circuit - 230v - 30-amp - Three Phase - Primary | AV100: ri.mio.main.media-item.0199713b-e2af-7291-b207-419560cb2e62 | AW100: Quote | BD100: POW00003 | BJ100: 0 | BL100: - | BO100: 12 | BP100: ri.mio.main.media-item.0199713b-e2af-7291-b207-419560cb2e62_11 | BT100: 1 | BU100: 2 | BV100: 100088117.OT1 | BX100: 44896 | BZ100: OT1 | CA100: OT1 | CM100: FALSE | CN100: 44030
... A120: QLI00119 | B120: ri.mio.main.media-item.0199713b-e2af-7291-b207-419560cb2e62 | C120: CAD | D120: Equinix Canada, Ltd. | F120: Quote-PO3000196864-EQUINIX-ATT+Wipro+Canada_Renewal+Post-Novation_MT1+OT1_1-222682409611+(37+months)+ATT+Signed+20230119.pdf | G120: Quote | H120: AT&T | L120: {"mimeType":"application/pdf","reference":{"type":"mediaSetViewItem","mediaSetViewItem":{"mediaSetRid":"ri.mio.main.media-set.7a7aadd5-adcf-42ac-9e71-12078d56f27e","mediaSetViewRid":"ri.mio.main.view.5660cab0-05c2-4700-94bc-c64529e38113","mediaItemRid":"ri.mio.main.media-item.0199713b-e2af-7291-b207-419560cb2e62"}}} | N120: PO3000196864 | P120: Equinix Canada, Ltd. | T120: FALSE | U120: -1 | AK120: ri.mio.main.media-item.0199713b-e2af-7291-b207-419560cb2e62_12_9 | AP120: AC Circuit - 230v - 30-amp - Three Phase - Redundant | AV120: ri.mio.main.media-item.0199713b-e2af-7291-b207-419560cb2e62 | AW120: Quote | BD120: POW00003 | BJ120: 0 | BL120: - | BO120: 12 | BP120: ri.mio.main.media-item.0199713b-e2af-7291-b207-419560cb2e62_11 | BT120: 1 | BU120: 9 | BV120: 100088124.OT1 | BX120: 44896 | BZ120: OT1 | CA120: OT1 | CM120: FALSE | CN120: 44030
A121: QLI00120 | B121: ri.mio.main.media-item.0199713b-e2af-7291-b207-419560cb2e62 | C121: CAD | D121: Equinix Canada, Ltd. | F121: Quote-PO3000196864-EQUINIX-ATT+Wipro+Canada_Renewal+Post-Novation_MT1+OT1_1-222682409611+(37+months)+ATT+Signed+20230119.pdf | G121: Quote | H121: AT&T | L121: {"mimeType":"application/pdf","reference":{"type":"mediaSetViewItem","mediaSetViewItem":{"mediaSetRid":"ri.mio.main.media-set.7a7aadd5-adcf-42ac-9e71-12078d56f27e","mediaSetViewRid":"ri.mio.main.view.5660cab0-05c2-4700-94bc-c64529e38113","mediaItemRid":"ri.mio.main.media-item.0199713b-e2af-7291-b207-419560cb2e62"}}} | N121: PO3000196864 | P121: Equinix Canada, Ltd. | T121: FALSE | U121: -1 | AK121: ri.mio.main.media-item.0199713b-e2af-7291-b207-419560cb2e62_13_1 | AP121: AC Circuit - 230v - 20-amp - Three Phase - Redundant | AV121: ri.mio.main.media-item.0199713b-e2af-7291-b207-419560cb2e62 | AW121: Quote | BD121: POW00003 | BJ121: 0 | BL121: - | BO121: 13 | BP121: ri.mio.main.media-item.0199713b-e2af-7291-b207-419560cb2e62_12 | BT121: 1 | BU121: 1 | BV121: 100088148_OT1 | BX121: 44896 | CI121: 0 | CM121: FALSE | CN121: 40270
A122: QLI00121 | B122: ri.mio.main.media-item.0199713b-e2af-7291-b207-419560cb2e62 | C122: CAD | D122: Equinix Canada, Ltd. | F122: Quote-PO3000196864-EQUINIX-ATT+Wipro+Canada_Renewal+Post-Novation_MT1+OT1_1-222682409611+(37+months)+ATT+Signed+20230119.pdf | G122: Quote | H122: AT&T | L122: {"mimeType":"application/pdf","reference":{"type":"mediaSetViewItem","mediaSetViewItem":{"mediaSetRid":"ri.mio.main.media-set.7a7aadd5-adcf-42ac-9e71-12078d56f27e","mediaSetViewRid":"ri.mio.main.view.5660cab0-05c2-4700-94bc-c64529e38113","mediaItemRid":"ri.mio.main.media-item.0199713b-e2af-7291-b207-419560cb2e62"}}} | N122: PO3000196864 | P122: Equinix Canada, Ltd. | T122: FALSE | U122: -1 | AK122: ri.mio.main.media-item.0199713b-e2af-7291-b207-419560cb2e62_13_10 | AP122: AC Circuit - 230v - 30-amp - Three Phase - Primary | AV122: ri.mio.main.media-item.0199713b-e2af-7291-b207-419560cb2e62 | AW122: Quote | BD122: POW00003 | BJ122: 0 | BL122: - | BO122: 13 | BP122: ri.mio.main.media-item.0199713b-e2af-7291-b207-419560cb2e62_12 | BT122: 1 | BU122: 10 | BV122: 100088157_OT1 | BX122: 44896 | CI122: 0 | CM122: FALSE | CN122: 40270
A123: QLI00122 | B123: ri.mio.main.media-item.0199713b-e2af-7291-b207-419560cb2e62 | C123: CAD | D123: Equinix Canada, Ltd. | F123: Quote-PO3000196864-EQUINIX-ATT+Wipro+Canada_Renewal+Post-Novation_MT1+OT1_1-222682409611+(37+months)+ATT+Signed+20230119.pdf | G123: Quote | H123: AT&T | L123: {"mimeType":"application/pdf","reference":{"type":"mediaSetViewItem","mediaSetViewItem":{"mediaSetRid":"ri.mio.main.media-set.7a7aadd5-adcf-42ac-9e71-12078d56f27e","mediaSetViewRid":"ri.mio.main.view.5660cab0-05c2-4700-94bc-c64529e38113","mediaItemRid":"ri.mio.main.media-item.0199713b-e2af-7291-b207-419560cb2e62"}}} | N123: PO3000196864 | P123: Equinix Canada, Ltd. | T123: FALSE | U123: -1 | AK123: ri.mio.main.media-item.0199713b-e2af-7291-b207-419560cb2e62_13_11 | AP123: AC Circuit - 230v - 20-amp - Three Phase - Redundant | AV123: ri.mio.main.media-item.0199713b-e2af-7291-b207-419560cb2e62 | AW123: Quote | BD123: POW00003 | BJ123: 0 | BL123: - | BO123: 13 | BP123: ri.mio.main.media-item.0199713b-e2af-7291-b207-419560cb2e62_12 | BT123: 1 | BU123: 11 | BV123: 100088158_OT1 | BX123: 44896 | CI123: 0 | CM123: FALSE | CN123: 40270
A124: QLI00123 | B124: ri.mio.main.media-item.0199713b-e2af-7291-b207-419560cb2e62 | C124: CAD | D124: Equinix Canada, Ltd. | F124: Quote-PO3000196864-EQUINIX-ATT+Wipro+Canada_Renewal+Post-Novation_MT1+OT1_1-222682409611+(37+months)+ATT+Signed+20230119.pdf | G124: Quote | H124: AT&T | L124: {"mimeType":"application/pdf","reference":{"type":"mediaSetViewItem","mediaSetViewItem":{"mediaSetRid":"ri.mio.main.media-set.7a7aadd5-adcf-42ac-9e71-12078d56f27e","mediaSetViewRid":"ri.mio.main.view.5660cab0-05c2-4700-94bc-c64529e38113","mediaItemRid":"ri.mio.main.media-item.0199713b-e2af-7291-b207-419560cb2e62"}}} | N124: PO3000196864 | P124: Equinix Canada, Ltd. | T124: FALSE | U124: -1 | AK124: ri.mio.main.media-item.0199713b-e2af-7291-b207-419560cb2e62_13_12 | AP124: AC Circuit - 230v - 20-amp - Three Phase - Redundant | AV124: ri.mio.main.media-item.0199713b-e2af-7291-b207-419560cb2e62 | AW124: Quote | BD124: POW00003 | BJ124: 0 | BL124: - | BO124: 13 | BP124: ri.mio.main.media-item.0199713b-e2af-7291-b207-419560cb2e62_12 | BT124: 1 | BU124: 12 | BV124: 100088160_OT1 | BX124: 44896 | CI124: 0 | CM124: FALSE | CN124: 40270
A125: QLI00124 | B125: ri.mio.main.media-item.0199713b-e2af-7291-b207-419560cb2e62 | C125: CAD | D125: Equinix Canada, Ltd. | F125: Quote-PO3000196864-EQUINIX-ATT+Wipro+Canada_Renewal+Post-Novation_MT1+OT1_1-222682409611+(37+months)+ATT+Signed+20230119.pdf | G125: Quote | H125: AT&T | L125: {"mimeType":"application/pdf","reference":{"type":"mediaSetViewItem","mediaSetViewItem":{"mediaSetRid":"ri.mio.main.media-set.7a7aadd5-adcf-42ac-9e71-12078d56f27e","mediaSetViewRid":"ri.mio.main.view.5660cab0-05c2-4700-94bc-c64529e38113","mediaItemRid":"ri.mio.main.media-item.0199713b-e2af-7291-b207-419560cb2e62"}}} | N125: PO3000196864 | P125: Equinix Canada, Ltd. | T125: FALSE | U125: -1 | AK125: ri.mio.main.media-item.0199713b-e2af-7291-b207-419560cb2e62_13_13 | AP125: AC Circuit - 230v - 20-amp - Three Phase - Primary | AV125: ri.mio.main.media-item.0199713b-e2af-7291-b207-419560cb2e62 | AW125: Quote | BD125: POW00003 | BJ125: 0 | BL125: - | BO125: 13 | BP125: ri.mio.main.media-item.0199713b-e2af-7291-b207-419560cb2e62_12 | BT125: 1 | BU125: 13 | BV125: 100088159_OT1 | BX125: 44896 | CI125: 0 | CM125: FALSE | CN125: 40270
A126: QLI00125 | B126: ri.mio.main.media-item.0199713b-e2af-7291-b207-419560cb2e62 | C126: CAD | D126: Equinix Canada, Ltd. | F126: Quote-PO3000196864-EQUINIX-ATT+Wipro+Canada_Renewal+Post-Novation_MT1+OT1_1-222682409611+(37+months)+ATT+Signed+20230119.pdf | G126: Quote | H126: AT&T | L126: {"mimeType":"application/pdf","reference":{"type":"mediaSetViewItem","mediaSetViewItem":{"mediaSetRid":"ri.mio.main.media-set.7a7aadd5-adcf-42ac-9e71-12078d56f27e","mediaSetViewRid":"ri.mio.main.view.5660cab0-05c2-4700-94bc-c64529e38113","mediaItemRid":"ri.mio.main.media-item.0199713b-e2af-7291-b207-419560cb2e62"}}} | N126: PO3000196864 | P126: Equinix Canada, Ltd. | T126: FALSE | U126: -1 | AK126: ri.mio.main.media-item.0199713b-e2af-7291-b207-419560cb2e62_13_2 | AP126: AC Circuit - 230v - 20-amp - Three Phase - Primary | AV126: ri.mio.main.media-item.0199713b-e2af-7291-b207-419560cb2e62 | AW126: Quote | BD126: POW00003 | BJ126: 0 | BL126: - | BO126: 13 | BP126: ri.mio.main.media-item.0199713b-e2af-7291-b207-419560cb2e62_12 | BT126: 1 | BU126: 2 | BV126: 100088149_OT1 | BX126: 44896 | CI126: 0 | CM126: FALSE | CN126: 40270
A127: QLI00126 | B127: ri.mio.main.media-item.0199713b-e2af-7291-b207-419560cb2e62 | C127: CAD | D127: Equinix Canada, Ltd. | F127: Quote-PO3000196864-EQUINIX-ATT+Wipro+Canada_Renewal+Post-Novation_MT1+OT1_1-222682409611+(37+months)+ATT+Signed+20230119.pdf | G127: Quote | H127: AT&T | L127: {"mimeType":"application/pdf","reference":{"type":"mediaSetViewItem","mediaSetViewItem":{"mediaSetRid":"ri.mio.main.media-set.7a7aadd5-adcf-42ac-9e71-12078d56f27e","mediaSetViewRid":"ri.mio.main.view.5660cab0-05c2-4700-94bc-c64529e38113","mediaItemRid":"ri.mio.main.media-item.0199713b-e2af-7291-b207-419560cb2e62"}}} | N127: PO3000196864 | P127: Equinix Canada, Ltd. | T127: FALSE | U127: -1 | AK127: ri.mio.main.media-item.0199713b-e2af-7291-b207-419560cb2e62_13_3 | AP127: AC Circuit - 230v - 20-amp - Three Phase - Redundant | AV127: ri.mio.main.media-item.0199713b-e2af-7291-b207-419560cb2e62 | AW127: Quote | BD127: POW00003 | BJ127: 0 | BL127: - | BO127: 13 | BP127: ri.mio.main.media-item.0199713b-e2af-7291-b207-419560cb2e62_12 | BT127: 1 | BU127: 3 | BV127: 100088150_OT1 | BX127: 44896 | CI127: 0 | CM127: FALSE | CN127: 40270
A128: QLI00127 | B128: ri.mio.main.media-item.0199713b-e2af-7291-b207-419560cb2e62 | C128: CAD | D128: Equinix Canada, Ltd. | F128: Quote-PO3000196864-EQUINIX-ATT+Wipro+Canada_Renewal+Post-Novation_MT1+OT1_1-222682409611+(37+months)+ATT+Signed+20230119.pdf | G128: Quote | H128: AT&T | L128: {"mimeType":"application/pdf","reference":{"type":"mediaSetViewItem","mediaSetViewItem":{"mediaSetRid":"ri.mio.main.media-set.7a7aadd5-adcf-42ac-9e71-12078d56f27e","mediaSetViewRid":"ri.mio.main.view.5660cab0-05c2-4700-94bc-c64529e38113","mediaItemRid":"ri.mio.main.media-item.0199713b-e2af-7291-b207-419560cb2e62"}}} | N128: PO3000196864 | P128: Equinix Canada, Ltd. | T128: FALSE | U128: -1 | AK128: ri.mio.main.media-item.0199713b-e2af-7291-b207-419560cb2e62_13_4 | AP128: AC Circuit - 230v - 20-amp - Three Phase - Redundant | AV128: ri.mio.main.media-item.0199713b-e2af-7291-b207-419560cb2e62 | AW128: Quote | BD128: POW00003 | BJ128: 0 | BL128: - | BO128: 13 | BP128: ri.mio.main.media-item.0199713b-e2af-7291-b207-419560cb2e62_12 | BT128: 1 | BU128: 4 | BV128: 100088151_OT1 | BX128: 44896 | CI128: 0 | CM128: FALSE | CN128: 40270
A129: QLI00128 | B129: ri.mio.main.media-item.0199713b-e2af-7291-b207-419560cb2e62 | C129: CAD | D129: Equinix Canada, Ltd. | F129: Quote-PO3000196864-EQUINIX-ATT+Wipro+Canada_Renewal+Post-Novation_MT1+OT1_1-222682409611+(37+months)+ATT+Signed+20230119.pdf | G129: Quote | H129: AT&T | L129: {"mimeType":"application/pdf","reference":{"type":"mediaSetViewItem","mediaSetViewItem":{"mediaSetRid":"ri.mio.main.media-set.7a7aadd5-adcf-42ac-9e71-12078d56f27e","mediaSetViewRid":"ri.mio.main.view.5660cab0-05c2-4700-94bc-c64529e38113","mediaItemRid":"ri.mio.main.media-item.0199713b-e2af-7291-b207-419560cb2e62"}}} | N129: PO3000196864 | P129: Equinix Canada, Ltd. | T129: FALSE | U129: -1 | AK129: ri.mio.main.media-item.0199713b-e2af-7291-b207-419560cb2e62_13_5 | AP129: AC Circuit - 230v - 20-amp - Three Phase - Redundant | AV129: ri.mio.main.media-item.0199713b-e2af-7291-b207-419560cb2e62 | AW129: Quote | BD129: POW00003 | BJ129: 0 | BL129: - | BO129: 13 | BP129: ri.mio.main.media-item.0199713b-e2af-7291-b207-419560cb2e62_12 | BT129: 1 | BU129: 5 | BV129: 100088152_OT1 | BX129: 44896 | CI129: 0 | CM129: FALSE | CN129: 40270
A130: QLI00129 | B130: ri.mio.main.media-item.0199713b-e2af-7291-b207-419560cb2e62 | C130: CAD | D130: Equinix Canada, Ltd. | F130: Quote-PO3000196864-EQUINIX-ATT+Wipro+Canada_Renewal+Post-Novation_MT1+OT1_1-222682409611+(37+months)+ATT+Signed+20230119.pdf | G130: Quote | H130: AT&T | L130: {"mimeType":"application/pdf","reference":{"type":"mediaSetViewItem","mediaSetViewItem":{"mediaSetRid":"ri.mio.main.media-set.7a7aadd5-adcf-42ac-9e71-12078d56f27e","mediaSetViewRid":"ri.mio.main.view.5660cab0-05c2-4700-94bc-c64529e38113","mediaItemRid":"ri.mio.main.media-item.0199713b-e2af-7291-b207-419560cb2e62"}}} | N130: PO3000196864 | P130: Equinix Canada, Ltd. | T130: FALSE | U130: -1 | AK130: ri.mio.main.media-item.0199713b-e2af-7291-b207-419560cb2e62_13_6 | AP130: AC Circuit - 230v - 20-amp - Three Phase - Primary | AV130: ri.mio.main.media-item.0199713b-e2af-7291-b207-419560cb2e62 | AW130: Quote | BD130: POW00003 | BJ130: 0 | BL130: - | BO130: 13 | BP130: ri.mio.main.media-item.0199713b-e2af-7291-b207-419560cb2e62_12 | BT130: 1 | BU130: 6 | BV130: 100088153_OT1 | BX130: 44896 | CI130: 0 | CM130: FALSE | CN130: 40270
A131: QLI00130 | B131: ri.mio.main.media-item.0199713b-e2af-7291-b207-419560cb2e62 | C131: CAD | D131: Equinix Canada, Ltd. | F131: Quote-PO3000196864-EQUINIX-ATT+Wipro+Canada_Renewal+Post-Novation_MT1+OT1_1-222682409611+(37+months)+ATT+Signed+20230119.pdf | G131: Quote | H131: AT&T | L131: {"mimeType":"application/pdf","reference":{"type":"mediaSetViewItem","mediaSetViewItem":{"mediaSetRid":"ri.mio.main.media-set.7a7aadd5-adcf-42ac-9e71-12078d56f27e","mediaSetViewRid":"ri.mio.main.view.5660cab0-05c2-4700-94bc-c64529e38113","mediaItemRid":"ri.mio.main.media-item.0199713b-e2af-7291-b207-419560cb2e62"}}} | N131: PO3000196864 | P131: Equinix Canada, Ltd. | T131: FALSE | U131: -1 | AK131: ri.mio.main.media-item.0199713b-e2af-7291-b207-419560cb2e62_13_7 | AP131: AC Circuit - 230v - 30-amp - Three Phase - Redundant | AV131: ri.mio.main.media-item.0199713b-e2af-7291-b207-419560cb2e62 | AW131: Quote | BD131: POW00003 | BJ131: 0 | BL131: - | BO131: 13 | BP131: ri.mio.main.media-item.0199713b-e2af-7291-b207-419560cb2e62_12 | BT131: 1 | BU131: 7 | BV131: 100088154_OT1 | BX131: 44896 | CI131: 0 | CM131: FALSE | CN131: 40270
A132: QLI00131 | B132: ri.mio.main.media-item.0199713b-e2af-7291-b207-419560cb2e62 | C132: CAD | D132: Equinix Canada, Ltd. | F132: Quote-PO3000196864-EQUINIX-ATT+Wipro+Canada_Renewal+Post-Novation_MT1+OT1_1-222682409611+(37+months)+ATT+Signed+20230119.pdf | G132: Quote | H132: AT&T | L132: {"mimeType":"application/pdf","reference":{"type":"mediaSetViewItem","mediaSetViewItem":{"mediaSetRid":"ri.mio.main.media-set.7a7aadd5-adcf-42ac-9e71-12078d56f27e","mediaSetViewRid":"ri.mio.main.view.5660cab0-05c2-4700-94bc-c64529e38113","mediaItemRid":"ri.mio.main.media-item.0199713b-e2af-7291-b207-419560cb2e62"}}} | N132: PO3000196864 | P132: Equinix Canada, Ltd. | T132: FALSE | U132: -1 | AK132: ri.mio.main.media-item.0199713b-e2af-7291-b207-419560cb2e62_13_8 | AP132: AC Circuit - 230v - 30-amp - Three Phase - Primary | AV132: ri.mio.main.media-item.0199713b-e2af-7291-b207-419560cb2e62 | AW132: Quote | BD132: POW00003 | BJ132: 0 | BL132: - | BO132: 13 | BP132: ri.mio.main.media-item.0199713b-e2af-7291-b207-419560cb2e62_12 | BT132: 1 | BU132: 8 | BV132: 100088155_OT1 | BX132: 44896 | CI132: 0 | CM132: FALSE | CN132: 40270
... A138: QLI00137 | B138: ri.mio.main.media-item.0199713b-e2af-7291-b207-419560cb2e62 | C138: CAD | D138: Equinix Canada, Ltd. | F138: Quote-PO3000196864-EQUINIX-ATT+Wipro+Canada_Renewal+Post-Novation_MT1+OT1_1-222682409611+(37+months)+ATT+Signed+20230119.pdf | G138: Quote | H138: AT&T | L138: {"mimeType":"application/pdf","reference":{"type":"mediaSetViewItem","mediaSetViewItem":{"mediaSetRid":"ri.mio.main.media-set.7a7aadd5-adcf-42ac-9e71-12078d56f27e","mediaSetViewRid":"ri.mio.main.view.5660cab0-05c2-4700-94bc-c64529e38113","mediaItemRid":"ri.mio.main.media-item.0199713b-e2af-7291-b207-419560cb2e62"}}} | N138: PO3000196864 | P138: Equinix Canada, Ltd. | T138: FALSE | U138: -1 | AK138: ri.mio.main.media-item.0199713b-e2af-7291-b207-419560cb2e62_14_13 | AP138: Cabinet - 4 KVA - Closed Cabinet | AV138: ri.mio.main.media-item.0199713b-e2af-7291-b207-419560cb2e62 | AW138: Quote | BD138: CAB00001 | BJ138: 0 | BL138: - | BO138: 14 | BP138: ri.mio.main.media-item.0199713b-e2af-7291-b207-419560cb2e62_13 | BT138: 1 | BU138: 13 | BV138: 0401-00087082 | BX138: 44896 | CI138: 0 | CM138: FALSE | CN138: 39248
A139: QLI00138 | B139: ri.mio.main.media-item.0199713b-e2af-7291-b207-419560cb2e62 | C139: CAD | D139: Equinix Canada, Ltd. | F139: Quote-PO3000196864-EQUINIX-ATT+Wipro+Canada_Renewal+Post-Novation_MT1+OT1_1-222682409611+(37+months)+ATT+Signed+20230119.pdf | G139: Quote | H139: AT&T | L139: {"mimeType":"application/pdf","reference":{"type":"mediaSetViewItem","mediaSetViewItem":{"mediaSetRid":"ri.mio.main.media-set.7a7aadd5-adcf-42ac-9e71-12078d56f27e","mediaSetViewRid":"ri.mio.main.view.5660cab0-05c2-4700-94bc-c64529e38113","mediaItemRid":"ri.mio.main.media-item.0199713b-e2af-7291-b207-419560cb2e62"}}} | N139: PO3000196864 | P139: Equinix Canada, Ltd. | T139: FALSE | U139: -1 | AK139: ri.mio.main.media-item.0199713b-e2af-7291-b207-419560cb2e62_14_14 | AP139: Cage - Customer Provided Cabinet - 12 Cabinets - 48 KVA | AV139: ri.mio.main.media-item.0199713b-e2af-7291-b207-419560cb2e62 | AW139: Quote | BD139: CAG00001 | BJ139: - | BL139: 16200 | BO139: 14 | BP139: ri.mio.main.media-item.0199713b-e2af-7291-b207-419560cb2e62_13 | BT139: 48 | BU139: 14 | BV139: 113915-00087064 | BX139: 44896 | CM139: FALSE | CN139: 39248
A140: QLI00139 | B140: ri.mio.main.media-item.0199713b-e2af-7291-b207-419560cb2e62 | C140: CAD | D140: Equinix Canada, Ltd. | F140: Quote-PO3000196864-EQUINIX-ATT+Wipro+Canada_Renewal+Post-Novation_MT1+OT1_1-222682409611+(37+months)+ATT+Signed+20230119.pdf | G140: Quote | H140: AT&T | L140: {"mimeType":"application/pdf","reference":{"type":"mediaSetViewItem","mediaSetViewItem":{"mediaSetRid":"ri.mio.main.media-set.7a7aadd5-adcf-42ac-9e71-12078d56f27e","mediaSetViewRid":"ri.mio.main.view.5660cab0-05c2-4700-94bc-c64529e38113","mediaItemRid":"ri.mio.main.media-item.0199713b-e2af-7291-b207-419560cb2e62"}}} | N140: PO3000196864 | P140: Equinix Canada, Ltd. | T140: FALSE | U140: -1 | AK140: ri.mio.main.media-item.0199713b-e2af-7291-b207-419560cb2e62_14_15 | AP140: Cabinet - 4 KVA - Closed Cabinet | AV140: ri.mio.main.media-item.0199713b-e2af-7291-b207-419560cb2e62 | AW140: Quote | BD140: CAB00001 | BJ140: 0 | BL140: - | BO140: 14 | BP140: ri.mio.main.media-item.0199713b-e2af-7291-b207-419560cb2e62_13 | BT140: 1 | BU140: 15 | BV140: 0304-00087092 | BX140: 44896 | CI140: 0 | CM140: FALSE | CN140: 39248
A141: QLI00140 | B141: ri.mio.main.media-item.0199713b-e2af-7291-b207-419560cb2e62 | C141: CAD | D141: Equinix Canada, Ltd. | F141: Quote-PO3000196864-EQUINIX-ATT+Wipro+Canada_Renewal+Post-Novation_MT1+OT1_1-222682409611+(37+months)+ATT+Signed+20230119.pdf | G141: Quote | H141: AT&T | L141: {"mimeType":"application/pdf","reference":{"type":"mediaSetViewItem","mediaSetViewItem":{"mediaSetRid":"ri.mio.main.media-set.7a7aadd5-adcf-42ac-9e71-12078d56f27e","mediaSetViewRid":"ri.mio.main.view.5660cab0-05c2-4700-94bc-c64529e38113","mediaItemRid":"ri.mio.main.media-item.0199713b-e2af-7291-b207-419560cb2e62"}}} | N141: PO3000196864 | P141: Equinix Canada, Ltd. | T141: FALSE | U141: -1 | AK141: ri.mio.main.media-item.0199713b-e2af-7291-b207-419560cb2e62_14_16 | AP141: Cabinet - 4 KVA - Closed Cabinet | AV141: ri.mio.main.media-item.0199713b-e2af-7291-b207-419560cb2e62 | AW141: Quote | BD141: CAB00001 | BJ141: 0 | BL141: - | BO141: 14 | BP141: ri.mio.main.media-item.0199713b-e2af-7291-b207-419560cb2e62_13 | BT141: 1 | BU141: 16 | BV141: 0302-00087089 | BX141: 44896 | CI141: 0 | CM141: FALSE | CN141: 39248
A142: QLI00141 | B142: ri.mio.main.media-item.0199713b-e2af-7291-b207-419560cb2e62 | C142: CAD | D142: Equinix Canada, Ltd. | F142: Quote-PO3000196864-EQUINIX-ATT+Wipro+Canada_Renewal+Post-Novation_MT1+OT1_1-222682409611+(37+months)+ATT+Signed+20230119.pdf | G142: Quote | H142: AT&T | L142: {"mimeType":"application/pdf","reference":{"type":"mediaSetViewItem","mediaSetViewItem":{"mediaSetRid":"ri.mio.main.media-set.7a7aadd5-adcf-42ac-9e71-12078d56f27e","mediaSetViewRid":"ri.mio.main.view.5660cab0-05c2-4700-94bc-c64529e38113","mediaItemRid":"ri.mio.main.media-item.0199713b-e2af-7291-b207-419560cb2e62"}}} | N142: PO3000196864 | P142: Equinix Canada, Ltd. | T142: FALSE | U142: -1 | AK142: ri.mio.main.media-item.0199713b-e2af-7291-b207-419560cb2e62_14_17 | AP142: Cabinet - 4 KVA - Closed Cabinet | AV142: ri.mio.main.media-item.0199713b-e2af-7291-b207-419560cb2e62 | AW142: Quote | BD142: CAB00001 | BJ142: 0 | BL142: - | BO142: 14 | BP142: ri.mio.main.media-item.0199713b-e2af-7291-b207-419560cb2e62_13 | BT142: 1 | BU142: 17 | BV142: 0210-00087084 | BX142: 44896 | CI142: 0 | CM142: FALSE | CN142: 39248
A143: QLI00142 | B143: ri.mio.main.media-item.0199713b-e2af-7291-b207-419560cb2e62 | C143: CAD | D143: Equinix Canada, Ltd. | F143: Quote-PO3000196864-EQUINIX-ATT+Wipro+Canada_Renewal+Post-Novation_MT1+OT1_1-222682409611+(37+months)+ATT+Signed+20230119.pdf | G143: Quote | H143: AT&T | L143: {"mimeType":"application/pdf","reference":{"type":"mediaSetViewItem","mediaSetViewItem":{"mediaSetRid":"ri.mio.main.media-set.7a7aadd5-adcf-42ac-9e71-12078d56f27e","mediaSetViewRid":"ri.mio.main.view.5660cab0-05c2-4700-94bc-c64529e38113","mediaItemRid":"ri.mio.main.media-item.0199713b-e2af-7291-b207-419560cb2e62"}}} | N143: PO3000196864 | P143: Equinix Canada, Ltd. | T143: FALSE | U143: -1 | AK143: ri.mio.main.media-item.0199713b-e2af-7291-b207-419560cb2e62_14_18 | AP143: Cabinet - 4 KVA - Closed Cabinet | AV143: ri.mio.main.media-item.0199713b-e2af-7291-b207-419560cb2e62 | AW143: Quote | BD143: CAB00001 | BJ143: 0 | BL143: - | BO143: 14 | BP143: ri.mio.main.media-item.0199713b-e2af-7291-b207-419560cb2e62_13 | BT143: 1 | BU143: 18 | BV143: 0204-00087088 | BX143: 44896 | CI143: 0 | CM143: FALSE | CN143: 39248
A144: QLI00143 | B144: ri.mio.main.media-item.0199713b-e2af-7291-b207-419560cb2e62 | C144: CAD | D144: Equinix Canada, Ltd. | F144: Quote-PO3000196864-EQUINIX-ATT+Wipro+Canada_Renewal+Post-Novation_MT1+OT1_1-222682409611+(37+months)+ATT+Signed+20230119.pdf | G144: Quote | H144: AT&T | L144: {"mimeType":"application/pdf","reference":{"type":"mediaSetViewItem","mediaSetViewItem":{"mediaSetRid":"ri.mio.main.media-set.7a7aadd5-adcf-42ac-9e71-12078d56f27e","mediaSetViewRid":"ri.mio.main.view.5660cab0-05c2-4700-94bc-c64529e38113","mediaItemRid":"ri.mio.main.media-item.0199713b-e2af-7291-b207-419560cb2e62"}}} | N144: PO3000196864 | P144: Equinix Canada, Ltd. | T144: FALSE | U144: -1 | AK144: ri.mio.main.media-item.0199713b-e2af-7291-b207-419560cb2e62_14_19 | AP144: Cabinet - 4 KVA - Closed Cabinet | AV144: ri.mio.main.media-item.0199713b-e2af-7291-b207-419560cb2e62 | AW144: Quote | BD144: CAB00001 | BJ144: 0 | BL144: - | BO144: 14 | BP144: ri.mio.main.media-item.0199713b-e2af-7291-b207-419560cb2e62_13 | BT144: 1 | BU144: 19 | BV144: 0305-00087003 | BX144: 44896 | CI144: 0 | CM144: FALSE | CN144: 39248
A145: QLI00144 | B145: ri.mio.main.media-item.0199713b-e2af-7291-b207-419560cb2e62 | C145: CAD | D145: Equinix Canada, Ltd. | F145: Quote-PO3000196864-EQUINIX-ATT+Wipro+Canada_Renewal+Post-Novation_MT1+OT1_1-222682409611+(37+months)+ATT+Signed+20230119.pdf | G145: Quote | H145: AT&T | L145: {"mimeType":"application/pdf","reference":{"type":"mediaSetViewItem","mediaSetViewItem":{"mediaSetRid":"ri.mio.main.media-set.7a7aadd5-adcf-42ac-9e71-12078d56f27e","mediaSetViewRid":"ri.mio.main.view.5660cab0-05c2-4700-94bc-c64529e38113","mediaItemRid":"ri.mio.main.media-item.0199713b-e2af-7291-b207-419560cb2e62"}}} | N145: PO3000196864 | P145: Equinix Canada, Ltd. | T145: FALSE | U145: -1 | AK145: ri.mio.main.media-item.0199713b-e2af-7291-b207-419560cb2e62_14_2 | AP145: AC Circuit - 230v - 20-amp - Three Phase - Primary | AV145: ri.mio.main.media-item.0199713b-e2af-7291-b207-419560cb2e62 | AW145: Quote | BD145: POW00003 | BJ145: 0 | BL145: - | BO145: 14 | BP145: ri.mio.main.media-item.0199713b-e2af-7291-b207-419560cb2e62_13 | BT145: 1 | BU145: 2 | BV145: 100088331_OT1 | BX145: 44896 | CI145: 0 | CM145: FALSE | CN145: 39248
A146: QLI00145 | B146: ri.mio.main.media-item.0199713b-e2af-7291-b207-419560cb2e62 | C146: CAD | D146: Equinix Canada, Ltd. | F146: Quote-PO3000196864-EQUINIX-ATT+Wipro+Canada_Renewal+Post-Novation_MT1+OT1_1-222682409611+(37+months)+ATT+Signed+20230119.pdf | G146: Quote | H146: AT&T | L146: {"mimeType":"application/pdf","reference":{"type":"mediaSetViewItem","mediaSetViewItem":{"mediaSetRid":"ri.mio.main.media-set.7a7aadd5-adcf-42ac-9e71-12078d56f27e","mediaSetViewRid":"ri.mio.main.view.5660cab0-05c2-4700-94bc-c64529e38113","mediaItemRid":"ri.mio.main.media-item.0199713b-e2af-7291-b207-419560cb2e62"}}} | N146: PO3000196864 | P146: Equinix Canada, Ltd. | T146: FALSE | U146: -1 | AK146: ri.mio.main.media-item.0199713b-e2af-7291-b207-419560cb2e62_14_20 | AP146: Cabinet - 4 KVA - Closed Cabinet | AV146: ri.mio.main.media-item.0199713b-e2af-7291-b207-419560cb2e62 | AW146: Quote | BD146: CAB00001 | BJ146: 0 | BL146: - | BO146: 14 | BP146: ri.mio.main.media-item.0199713b-e2af-7291-b207-419560cb2e62_13 | BT146: 1 | BU146: 20 | BV146: 0204-00087087 | BX146: 44896 | CI146: 0 | CM146: FALSE | CN146: 39248
A147: QLI00146 | B147: ri.mio.main.media-item.0199713b-e2af-7291-b207-419560cb2e62 | C147: CAD | D147: Equinix Canada, Ltd. | F147: Quote-PO3000196864-EQUINIX-ATT+Wipro+Canada_Renewal+Post-Novation_MT1+OT1_1-222682409611+(37+months)+ATT+Signed+20230119.pdf | G147: Quote | H147: AT&T | L147: {"mimeType":"application/pdf","reference":{"type":"mediaSetViewItem","mediaSetViewItem":{"mediaSetRid":"ri.mio.main.media-set.7a7aadd5-adcf-42ac-9e71-12078d56f27e","mediaSetViewRid":"ri.mio.main.view.5660cab0-05c2-4700-94bc-c64529e38113","mediaItemRid":"ri.mio.main.media-item.0199713b-e2af-7291-b207-419560cb2e62"}}} | N147: PO3000196864 | P147: Equinix Canada, Ltd. | T147: FALSE | U147: -1 | AK147: ri.mio.main.media-item.0199713b-e2af-7291-b207-419560cb2e62_14_21 | AP147: Cabinet - 4 KVA - Closed Cabinet | AV147: ri.mio.main.media-item.0199713b-e2af-7291-b207-419560cb2e62 | AW147: Quote | BD147: CAB00001 | BJ147: 0 | BL147: - | BO147: 14 | BP147: ri.mio.main.media-item.0199713b-e2af-7291-b207-419560cb2e62_13 | BT147: 1 | BU147: 21 | BV147: 0204-00087087 | BX147: 44896 | CI147: 0 | CM147: FALSE | CN147: 39248
A148: QLI00147 | B148: ri.mio.main.media-item.0199713b-e2af-7291-b207-419560cb2e62 | C148: CAD | D148: Equinix Canada, Ltd. | F148: Quote-PO3000196864-EQUINIX-ATT+Wipro+Canada_Renewal+Post-Novation_MT1+OT1_1-222682409611+(37+months)+ATT+Signed+20230119.pdf | G148: Quote | H148: AT&T | L148: {"mimeType":"application/pdf","reference":{"type":"mediaSetViewItem","mediaSetViewItem":{"mediaSetRid":"ri.mio.main.media-set.7a7aadd5-adcf-42ac-9e71-12078d56f27e","mediaSetViewRid":"ri.mio.main.view.5660cab0-05c2-4700-94bc-c64529e38113","mediaItemRid":"ri.mio.main.media-item.0199713b-e2af-7291-b207-419560cb2e62"}}} | N148: PO3000196864 | P148: Equinix Canada, Ltd. | T148: FALSE | U148: -1 | AK148: ri.mio.main.media-item.0199713b-e2af-7291-b207-419560cb2e62_14_22 | AP148: Cross Connect | AV148: ri.mio.main.media-item.0199713b-e2af-7291-b207-419560cb2e62 | AW148: Quote | BD148: CC00001 | BJ148: 320 | BL148: 0 | BO148: 14 | BP148: ri.mio.main.media-item.0199713b-e2af-7291-b207-419560cb2e62_13 | BT148: 1 | BU148: 22 | BV148: 7-10000497724 | BX148: 44896 | CI148: 320 | CM148: FALSE | CN148: 39248
A149: QLI00148 | B149: ri.mio.main.media-item.0199713b-e2af-7291-b207-419560cb2e62 | C149: CAD | D149: Equinix Canada, Ltd. | F149: Quote-PO3000196864-EQUINIX-ATT+Wipro+Canada_Renewal+Post-Novation_MT1+OT1_1-222682409611+(37+months)+ATT+Signed+20230119.pdf | G149: Quote | H149: AT&T | L149: {"mimeType":"application/pdf","reference":{"type":"mediaSetViewItem","mediaSetViewItem":{"mediaSetRid":"ri.mio.main.media-set.7a7aadd5-adcf-42ac-9e71-12078d56f27e","mediaSetViewRid":"ri.mio.main.view.5660cab0-05c2-4700-94bc-c64529e38113","mediaItemRid":"ri.mio.main.media-item.0199713b-e2af-7291-b207-419560cb2e62"}}} | N149: PO3000196864 | P149: Equinix Canada, Ltd. | T149: FALSE | U149: -1 | AK149: ri.mio.main.media-item.0199713b-e2af-7291-b207-419560cb2e62_14_23 | AP149: Network Cable Connection - UTP - Z-side IBX- OT1 | AV149: ri.mio.main.media-item.0199713b-e2af-7291-b207-419560cb2e62 | AW149: Quote | BD149: CC00001 | BJ149: - | BL149: 320 | BO149: 14 | BP149: ri.mio.main.media-item.0199713b-e2af-7291-b207-419560cb2e62_13 | BT149: 1 | BU149: 23 | BV149: 1000041390 | BX149: 44896 | BZ149: OT1 | CM149: FALSE | CN149: 39248
A150: QLI00149 | B150: ri.mio.main.media-item.0199713b-e2af-7291-b207-419560cb2e62 | C150: CAD | D150: Equinix Canada, Ltd. | F150: Quote-PO3000196864-EQUINIX-ATT+Wipro+Canada_Renewal+Post-Novation_MT1+OT1_1-222682409611+(37+months)+ATT+Signed+20230119.pdf | G150: Quote | H150: AT&T | L150: {"mimeType":"application/pdf","reference":{"type":"mediaSetViewItem","mediaSetViewItem":{"mediaSetRid":"ri.mio.main.media-set.7a7aadd5-adcf-42ac-9e71-12078d56f27e","mediaSetViewRid":"ri.mio.main.view.5660cab0-05c2-4700-94bc-c64529e38113","mediaItemRid":"ri.mio.main.media-item.0199713b-e2af-7291-b207-419560cb2e62"}}} | N150: PO3000196864 | P150: Equinix Canada, Ltd. | T150: FALSE | U150: -1 | AK150: ri.mio.main.media-item.0199713b-e2af-7291-b207-419560cb2e62_14_24 | AP150: Cross Connect | AV150: ri.mio.main.media-item.0199713b-e2af-7291-b207-419560cb2e62 | AW150: Quote | BD150: CC00001 | BJ150: 320 | BL150: 0 | BO150: 14 | BP150: ri.mio.main.media-item.0199713b-e2af-7291-b207-419560cb2e62_13 | BT150: 1 | BU150: 24 | BV150: 7-10000396651 | BX150: 44896 | CI150: 320 | CM150: FALSE | CN150: 39248
A151: QLI00150 | B151: ri.mio.main.media-item.0199713b-e2af-7291-b207-419560cb2e62 | C151: CAD | D151: Equinix Canada, Ltd. | F151: Quote-PO3000196864-EQUINIX-ATT+Wipro+Canada_Renewal+Post-Novation_MT1+OT1_1-222682409611+(37+months)+ATT+Signed+20230119.pdf | G151: Quote | H151: AT&T | L151: {"mimeType":"application/pdf","reference":{"type":"mediaSetViewItem","mediaSetViewItem":{"mediaSetRid":"ri.mio.main.media-set.7a7aadd5-adcf-42ac-9e71-12078d56f27e","mediaSetViewRid":"ri.mio.main.view.5660cab0-05c2-4700-94bc-c64529e38113","mediaItemRid":"ri.mio.main.media-item.0199713b-e2af-7291-b207-419560cb2e62"}}} | N151: PO3000196864 | P151: Equinix Canada, Ltd. | T151: FALSE | U151: -1 | AK151: ri.mio.main.media-item.0199713b-e2af-7291-b207-419560cb2e62_14_25 | AP151: Network Cable Connection - Single-Mode Fiber | AV151: ri.mio.main.media-item.0199713b-e2af-7291-b207-419560cb2e62 | AW151: Quote | BD151: CC00001 | BJ151: - | BL151: 320 | BO151: 14 | BP151: ri.mio.main.media-item.0199713b-e2af-7291-b207-419560cb2e62_13 | BT151: 1 | BU151: 25 | BV151: 1000099154 | BX151: 44896 | CM151: FALSE | CN151: 39248
A152: QLI00151 | B152: ri.mio.main.media-item.0199713b-e2af-7291-b207-419560cb2e62 | C152: CAD | D152: Equinix Canada, Ltd. | F152: Quote-PO3000196864-EQUINIX-ATT+Wipro+Canada_Renewal+Post-Novation_MT1+OT1_1-222682409611+(37+months)+ATT+Signed+20230119.pdf | G152: Quote | H152: AT&T | L152: {"mimeType":"application/pdf","reference":{"type":"mediaSetViewItem","mediaSetViewItem":{"mediaSetRid":"ri.mio.main.media-set.7a7aadd5-adcf-42ac-9e71-12078d56f27e","mediaSetViewRid":"ri.mio.main.view.5660cab0-05c2-4700-94bc-c64529e38113","mediaItemRid":"ri.mio.main.media-item.0199713b-e2af-7291-b207-419560cb2e62"}}} | N152: PO3000196864 | P152: Equinix Canada, Ltd. | T152: FALSE | U152: -1 | AK152: ri.mio.main.media-item.0199713b-e2af-7291-b207-419560cb2e62_14_26 | AP152: Cross Connect | AV152: ri.mio.main.media-item.0199713b-e2af-7291-b207-419560cb2e62 | AW152: Quote | BD152: CC00001 | BJ152: 320 | BL152: 0 | BO152: 14 | BP152: ri.mio.main.media-item.0199713b-e2af-7291-b207-419560cb2e62_13 | BT152: 1 | BU152: 26 | BV152: 7-10000395955 | BX152: 44896 | CI152: 320 | CM152: FALSE | CN152: 39248
A153: QLI00152 | B153: ri.mio.main.media-item.0199713b-e2af-7291-b207-419560cb2e62 | C153: CAD | D153: Equinix Canada, Ltd. | F153: Quote-PO3000196864-EQUINIX-ATT+Wipro+Canada_Renewal+Post-Novation_MT1+OT1_1-222682409611+(37+months)+ATT+Signed+20230119.pdf | G153: Quote | H153: AT&T | L153: {"mimeType":"application/pdf","reference":{"type":"mediaSetViewItem","mediaSetViewItem":{"mediaSetRid":"ri.mio.main.media-set.7a7aadd5-adcf-42ac-9e71-12078d56f27e","mediaSetViewRid":"ri.mio.main.view.5660cab0-05c2-4700-94bc-c64529e38113","mediaItemRid":"ri.mio.main.media-item.0199713b-e2af-7291-b207-419560cb2e62"}}} | N153: PO3000196864 | P153: Equinix Canada, Ltd. | T153: FALSE | U153: -1 | AK153: ri.mio.main.media-item.0199713b-e2af-7291-b207-419560cb2e62_14_27 | AP153: Network Cable Connection - UTP - Z-side IBX- OT1 | AV153: ri.mio.main.media-item.0199713b-e2af-7291-b207-419560cb2e62 | AW153: Quote | BD153: CC00001 | BJ153: - | BL153: 320 | BO153: 14 | BP153: ri.mio.main.media-item.0199713b-e2af-7291-b207-419560cb2e62_13 | BT153: 1 | BU153: 27 | BV153: 1000099591 | BX153: 44896 | BZ153: OT1 | CM153: FALSE | CN153: 39248
A154: QLI00153 | B154: ri.mio.main.media-item.0199713b-e2af-7291-b207-419560cb2e62 | C154: CAD | D154: Equinix Canada, Ltd. | F154: Quote-PO3000196864-EQUINIX-ATT+Wipro+Canada_Renewal+Post-Novation_MT1+OT1_1-222682409611+(37+months)+ATT+Signed+20230119.pdf | G154: Quote | H154: AT&T | L154: {"mimeType":"application/pdf","reference":{"type":"mediaSetViewItem","mediaSetViewItem":{"mediaSetRid":"ri.mio.main.media-set.7a7aadd5-adcf-42ac-9e71-12078d56f27e","mediaSetViewRid":"ri.mio.main.view.5660cab0-05c2-4700-94bc-c64529e38113","mediaItemRid":"ri.mio.main.media-item.0199713b-e2af-7291-b207-419560cb2e62"}}} | N154: PO3000196864 | P154: Equinix Canada, Ltd. | T154: FALSE | U154: -1 | AK154: ri.mio.main.media-item.0199713b-e2af-7291-b207-419560cb2e62_14_28 | AP154: Cross Connect | AV154: ri.mio.main.media-item.0199713b-e2af-7291-b207-419560cb2e62 | AW154: Quote | BD154: CC00001 | BJ154: 320 | BL154: 0 | BO154: 14 | BP154: ri.mio.main.media-item.0199713b-e2af-7291-b207-419560cb2e62_13 | BT154: 1 | BU154: 28 | BV154: 7-10000395958 | BX154: 44896 | CI154: 320 | CM154: FALSE | CN154: 39248
A155: QLI00154 | B155: ri.mio.main.media-item.0199713b-e2af-7291-b207-419560cb2e62 | C155: CAD | D155: Equinix Canada, Ltd. | F155: Quote-PO3000196864-EQUINIX-ATT+Wipro+Canada_Renewal+Post-Novation_MT1+OT1_1-222682409611+(37+months)+ATT+Signed+20230119.pdf | G155: Quote | H155: AT&T | L155: {"mimeType":"application/pdf","reference":{"type":"mediaSetViewItem","mediaSetViewItem":{"mediaSetRid":"ri.mio.main.media-set.7a7aadd5-adcf-42ac-9e71-12078d56f27e","mediaSetViewRid":"ri.mio.main.view.5660cab0-05c2-4700-94bc-c64529e38113","mediaItemRid":"ri.mio.main.media-item.0199713b-e2af-7291-b207-419560cb2e62"}}} | N155: PO3000196864 | P155: Equinix Canada, Ltd. | T155: FALSE | U155: -1 | AK155: ri.mio.main.media-item.0199713b-e2af-7291-b207-419560cb2e62_14_29 | AP155: Network Cable Connection - UTP - Z-side IBX- OT1 | AV155: ri.mio.main.media-item.0199713b-e2af-7291-b207-419560cb2e62 | AW155: Quote | BD155: CC00001 | BJ155: - | BL155: 320 | BO155: 14 | BP155: ri.mio.main.media-item.0199713b-e2af-7291-b207-419560cb2e62_13 | BT155: 1 | BU155: 29 | BV155: 1000099592 | BX155: 44896 | BZ155: OT1 | CM155: FALSE | CN155: 39248
A156: QLI00155 | B156: ri.mio.main.media-item.0199713b-e2af-7291-b207-419560cb2e62 | C156: CAD | D156: Equinix Canada, Ltd. | F156: Quote-PO3000196864-EQUINIX-ATT+Wipro+Canada_Renewal+Post-Novation_MT1+OT1_1-222682409611+(37+months)+ATT+Signed+20230119.pdf | G156: Quote | H156: AT&T | L156: {"mimeType":"application/pdf","reference":{"type":"mediaSetViewItem","mediaSetViewItem":{"mediaSetRid":"ri.mio.main.media-set.7a7aadd5-adcf-42ac-9e71-12078d56f27e","mediaSetViewRid":"ri.mio.main.view.5660cab0-05c2-4700-94bc-c64529e38113","mediaItemRid":"ri.mio.main.media-item.0199713b-e2af-7291-b207-419560cb2e62"}}} | N156: PO3000196864 | P156: Equinix Canada, Ltd. | T156: FALSE | U156: -1 | AK156: ri.mio.main.media-item.0199713b-e2af-7291-b207-419560cb2e62_14_3 | AP156: AC Circuit - 230v - 20-amp - Three Phase - Redundant | AV156: ri.mio.main.media-item.0199713b-e2af-7291-b207-419560cb2e62 | AW156: Quote | BD156: POW00003 | BJ156: 0 | BL156: - | BO156: 14 | BP156: ri.mio.main.media-item.0199713b-e2af-7291-b207-419560cb2e62_13 | BT156: 1 | BU156: 3 | BV156: 100088284_OT1 | BX156: 44896 | CI156: 0 | CM156: FALSE | CN156: 39248
A157: QLI00156 | B157: ri.mio.main.media-item.0199713b-e2af-7291-b207-419560cb2e62 | C157: CAD | D157: Equinix Canada, Ltd. | F157: Quote-PO3000196864-EQUINIX-ATT+Wipro+Canada_Renewal+Post-Novation_MT1+OT1_1-222682409611+(37+months)+ATT+Signed+20230119.pdf | G157: Quote | H157: AT&T | L157: {"mimeType":"application/pdf","reference":{"type":"mediaSetViewItem","mediaSetViewItem":{"mediaSetRid":"ri.mio.main.media-set.7a7aadd5-adcf-42ac-9e71-12078d56f27e","mediaSetViewRid":"ri.mio.main.view.5660cab0-05c2-4700-94bc-c64529e38113","mediaItemRid":"ri.mio.main.media-item.0199713b-e2af-7291-b207-419560cb2e62"}}} | N157: PO3000196864 | P157: Equinix Canada, Ltd. | T157: FALSE | U157: -1 | AK157: ri.mio.main.media-item.0199713b-e2af-7291-b207-419560cb2e62_14_30 | AP157: Cross Connect | AV157: ri.mio.main.media-item.0199713b-e2af-7291-b207-419560cb2e62 | AW157: Quote | BD157: CC00001 | BJ157: 320 | BL157: 0 | BO157: 14 | BP157: ri.mio.main.media-item.0199713b-e2af-7291-b207-419560cb2e62_13 | BT157: 1 | BU157: 30 | BV157: 7-10000398599 | BX157: 44896 | CI157: 320 | CM157: FALSE | CN157: 39248
A158: QLI00157 | B158: ri.mio.main.media-item.0199713b-e2af-7291-b207-419560cb2e62 | C158: CAD | D158: Equinix Canada, Ltd. | F158: Quote-PO3000196864-EQUINIX-ATT+Wipro+Canada_Renewal+Post-Novation_MT1+OT1_1-222682409611+(37+months)+ATT+Signed+20230119.pdf | G158: Quote | H158: AT&T | L158: {"mimeType":"application/pdf","reference":{"type":"mediaSetViewItem","mediaSetViewItem":{"mediaSetRid":"ri.mio.main.media-set.7a7aadd5-adcf-42ac-9e71-12078d56f27e","mediaSetViewRid":"ri.mio.main.view.5660cab0-05c2-4700-94bc-c64529e38113","mediaItemRid":"ri.mio.main.media-item.0199713b-e2af-7291-b207-419560cb2e62"}}} | N158: PO3000196864 | P158: Equinix Canada, Ltd. | T158: FALSE | U158: -1 | AK158: ri.mio.main.media-item.0199713b-e2af-7291-b207-419560cb2e62_14_31 | AP158: Network Cable Connection - Single-Mode Fiber | AV158: ri.mio.main.media-item.0199713b-e2af-7291-b207-419560cb2e62 | AW158: Quote | BD158: CC00001 | BJ158: - | BL158: 320 | BO158: 14 | BP158: ri.mio.main.media-item.0199713b-e2af-7291-b207-419560cb2e62_13 | BT158: 1 | BU158: 31 | BV158: 1000143089 | BX158: 44896 | CM158: FALSE | CN158: 39248
A159: QLI00158 | B159: ri.mio.main.media-item.0199713b-e2af-7291-b207-419560cb2e62 | C159: CAD | D159: Equinix Canada, Ltd. | F159: Quote-PO3000196864-EQUINIX-ATT+Wipro+Canada_Renewal+Post-Novation_MT1+OT1_1-222682409611+(37+months)+ATT+Signed+20230119.pdf | G159: Quote | H159: AT&T | L159: {"mimeType":"application/pdf","reference":{"type":"mediaSetViewItem","mediaSetViewItem":{"mediaSetRid":"ri.mio.main.media-set.7a7aadd5-adcf-42ac-9e71-12078d56f27e","mediaSetViewRid":"ri.mio.main.view.5660cab0-05c2-4700-94bc-c64529e38113","mediaItemRid":"ri.mio.main.media-item.0199713b-e2af-7291-b207-419560cb2e62"}}} | N159: PO3000196864 | P159: Equinix Canada, Ltd. | T159: FALSE | U159: -1 | AK159: ri.mio.main.media-item.0199713b-e2af-7291-b207-419560cb2e62_14_32 | AP159: Cross Connect | AV159: ri.mio.main.media-item.0199713b-e2af-7291-b207-419560cb2e62 | AW159: Quote | BD159: CC00001 | BJ159: 320 | BL159: 0 | BO159: 14 | BP159: ri.mio.main.media-item.0199713b-e2af-7291-b207-419560cb2e62_13 | BT159: 1 | BU159: 32 | BV159: 7-10000395913 | BX159: 44896 | CI159: 320 | CM159: FALSE | CN159: 39248
A160: QLI00159 | B160: ri.mio.main.media-item.0199713b-e2af-7291-b207-419560cb2e62 | C160: CAD | D160: Equinix Canada, Ltd. | F160: Quote-PO3000196864-EQUINIX-ATT+Wipro+Canada_Renewal+Post-Novation_MT1+OT1_1-222682409611+(37+months)+ATT+Signed+20230119.pdf | G160: Quote | H160: AT&T | L160: {"mimeType":"application/pdf","reference":{"type":"mediaSetViewItem","mediaSetViewItem":{"mediaSetRid":"ri.mio.main.media-set.7a7aadd5-adcf-42ac-9e71-12078d56f27e","mediaSetViewRid":"ri.mio.main.view.5660cab0-05c2-4700-94bc-c64529e38113","mediaItemRid":"ri.mio.main.media-item.0199713b-e2af-7291-b207-419560cb2e62"}}} | N160: PO3000196864 | P160: Equinix Canada, Ltd. | T160: FALSE | U160: -1 | AK160: ri.mio.main.media-item.0199713b-e2af-7291-b207-419560cb2e62_14_33 | AP160: Network Cable Connection - Single-Mode Fiber | AV160: ri.mio.main.media-item.0199713b-e2af-7291-b207-419560cb2e62 | AW160: Quote | BD160: CC00001 | BJ160: - | BL160: 320 | BO160: 14 | BP160: ri.mio.main.media-item.0199713b-e2af-7291-b207-419560cb2e62_13 | BT160: 1 | BU160: 33 | BV160: 1000091511 | BX160: 44896 | CM160: FALSE | CN160: 39248
A161: QLI00160 | B161: ri.mio.main.media-item.0199713b-e2af-7291-b207-419560cb2e62 | C161: CAD | D161: Equinix Canada, Ltd. | F161: Quote-PO3000196864-EQUINIX-ATT+Wipro+Canada_Renewal+Post-Novation_MT1+OT1_1-222682409611+(37+months)+ATT+Signed+20230119.pdf | G161: Quote | H161: AT&T | L161: {"mimeType":"application/pdf","reference":{"type":"mediaSetViewItem","mediaSetViewItem":{"mediaSetRid":"ri.mio.main.media-set.7a7aadd5-adcf-42ac-9e71-12078d56f27e","mediaSetViewRid":"ri.mio.main.view.5660cab0-05c2-4700-94bc-c64529e38113","mediaItemRid":"ri.mio.main.media-item.0199713b-e2af-7291-b207-419560cb2e62"}}} | N161: PO3000196864 | P161: Equinix Canada, Ltd. | T161: FALSE | U161: -1 | AK161: ri.mio.main.media-item.0199713b-e2af-7291-b207-419560cb2e62_14_4 | AP161: AC Circuit - 230v - 20-amp - Three Phase - Primary | AV161: ri.mio.main.media-item.0199713b-e2af-7291-b207-419560cb2e62 | AW161: Quote | BD161: POW00003 | BJ161: 0 | BL161: - | BO161: 14 | BP161: ri.mio.main.media-item.0199713b-e2af-7291-b207-419560cb2e62_13 | BT161: 1 | BU161: 4 | BV161: 100088283_OT1 | BX161: 44896 | CI161: 0 | CM161: FALSE | CN161: 39248
A162: QLI00161 | B162: ri.mio.main.media-item.0199713b-e2af-7291-b207-419560cb2e62 | C162: CAD | D162: Equinix Canada, Ltd. | F162: Quote-PO3000196864-EQUINIX-ATT+Wipro+Canada_Renewal+Post-Novation_MT1+OT1_1-222682409611+(37+months)+ATT+Signed+20230119.pdf | G162: Quote | H162: AT&T | L162: {"mimeType":"application/pdf","reference":{"type":"mediaSetViewItem","mediaSetViewItem":{"mediaSetRid":"ri.mio.main.media-set.7a7aadd5-adcf-42ac-9e71-12078d56f27e","mediaSetViewRid":"ri.mio.main.view.5660cab0-05c2-4700-94bc-c64529e38113","mediaItemRid":"ri.mio.main.media-item.0199713b-e2af-7291-b207-419560cb2e62"}}} | N162: PO3000196864 | P162: Equinix Canada, Ltd. | T162: FALSE | U162: -1 | AK162: ri.mio.main.media-item.0199713b-e2af-7291-b207-419560cb2e62_14_5 | AP162: AC Circuit - 230v - 20-amp - Three Phase - Primary | AV162: ri.mio.main.media-item.0199713b-e2af-7291-b207-419560cb2e62 | AW162: Quote | BD162: POW00003 | BJ162: 0 | BL162: - | BO162: 14 | BP162: ri.mio.main.media-item.0199713b-e2af-7291-b207-419560cb2e62_13 | BT162: 1 | BU162: 5 | BV162: 100088279_OT1 | BX162: 44896 | CI162: 0 | CM162: FALSE | CN162: 39248
A163: QLI00162 | B163: ri.mio.main.media-item.0199713b-e2af-7291-b207-419560cb2e62 | C163: CAD | D163: Equinix Canada, Ltd. | F163: Quote-PO3000196864-EQUINIX-ATT+Wipro+Canada_Renewal+Post-Novation_MT1+OT1_1-222682409611+(37+months)+ATT+Signed+20230119.pdf | G163: Quote | H163: AT&T | L163: {"mimeType":"application/pdf","reference":{"type":"mediaSetViewItem","mediaSetViewItem":{"mediaSetRid":"ri.mio.main.media-set.7a7aadd5-adcf-42ac-9e71-12078d56f27e","mediaSetViewRid":"ri.mio.main.view.5660cab0-05c2-4700-94bc-c64529e38113","mediaItemRid":"ri.mio.main.media-item.0199713b-e2af-7291-b207-419560cb2e62"}}} | N163: PO3000196864 | P163: Equinix Canada, Ltd. | T163: FALSE | U163: -1 | AK163: ri.mio.main.media-item.0199713b-e2af-7291-b207-419560cb2e62_14_6 | AP163: AC Circuit - 230v - 20-amp - Three Phase - Redundant | AV163: ri.mio.main.media-item.0199713b-e2af-7291-b207-419560cb2e62 | AW163: Quote | BD163: POW00003 | BJ163: 0 | BL163: - | BO163: 14 | BP163: ri.mio.main.media-item.0199713b-e2af-7291-b207-419560cb2e62_13 | BT163: 1 | BU163: 6 | BV163: 100088300_OT1 | BX163: 44896 | CI163: 0 | CM163: FALSE | CN163: 39248
A164: QLI00163 | B164: ri.mio.main.media-item.0199713b-e2af-7291-b207-419560cb2e62 | C164: CAD | D164: Equinix Canada, Ltd. | F164: Quote-PO3000196864-EQUINIX-ATT+Wipro+Canada_Renewal+Post-Novation_MT1+OT1_1-222682409611+(37+months)+ATT+Signed+20230119.pdf | G164: Quote | H164: AT&T | L164: {"mimeType":"application/pdf","reference":{"type":"mediaSetViewItem","mediaSetViewItem":{"mediaSetRid":"ri.mio.main.media-set.7a7aadd5-adcf-42ac-9e71-12078d56f27e","mediaSetViewRid":"ri.mio.main.view.5660cab0-05c2-4700-94bc-c64529e38113","mediaItemRid":"ri.mio.main.media-item.0199713b-e2af-7291-b207-419560cb2e62"}}} | N164: PO3000196864 | P164: Equinix Canada, Ltd. | T164: FALSE | U164: -1 | AK164: ri.mio.main.media-item.0199713b-e2af-7291-b207-419560cb2e62_14_7 | AP164: AC Circuit - 230v - 20-amp - Three Phase - Primary | AV164: ri.mio.main.media-item.0199713b-e2af-7291-b207-419560cb2e62 | AW164: Quote | BD164: POW00003 | BJ164: 0 | BL164: - | BO164: 14 | BP164: ri.mio.main.media-item.0199713b-e2af-7291-b207-419560cb2e62_13 | BT164: 1 | BU164: 7 | BV164: 100088323_OT1 | BX164: 44896 | CI164: 0 | CM164: FALSE | CN164: 39248
A165: QLI00164 | B165: ri.mio.main.media-item.0199713b-e2af-7291-b207-419560cb2e62 | C165: CAD | D165: Equinix Canada, Ltd. | F165: Quote-PO3000196864-EQUINIX-ATT+Wipro+Canada_Renewal+Post-Novation_MT1+OT1_1-222682409611+(37+months)+ATT+Signed+20230119.pdf | G165: Quote | H165: AT&T | L165: {"mimeType":"application/pdf","reference":{"type":"mediaSetViewItem","mediaSetViewItem":{"mediaSetRid":"ri.mio.main.media-set.7a7aadd5-adcf-42ac-9e71-12078d56f27e","mediaSetViewRid":"ri.mio.main.view.5660cab0-05c2-4700-94bc-c64529e38113","mediaItemRid":"ri.mio.main.media-item.0199713b-e2af-7291-b207-419560cb2e62"}}} | N165: PO3000196864 | P165: Equinix Canada, Ltd. | T165: FALSE | U165: -1 | AK165: ri.mio.main.media-item.0199713b-e2af-7291-b207-419560cb2e62_14_8 | AP165: AC Circuit - 230v - 20-amp - Three Phase - Redundant | AV165: ri.mio.main.media-item.0199713b-e2af-7291-b207-419560cb2e62 | AW165: Quote | BD165: POW00003 | BJ165: 0 | BL165: - | BO165: 14 | BP165: ri.mio.main.media-item.0199713b-e2af-7291-b207-419560cb2e62_13 | BT165: 1 | BU165: 8 | BV165: 100088280_OT1 | BX165: 44896 | CI165: 0 | CM165: FALSE | CN165: 39248
A166: QLI00165 | B166: ri.mio.main.media-item.0199713b-e2af-7291-b207-419560cb2e62 | C166: CAD | D166: Equinix Canada, Ltd. | F166: Quote-PO3000196864-EQUINIX-ATT+Wipro+Canada_Renewal+Post-Novation_MT1+OT1_1-222682409611+(37+months)+ATT+Signed+20230119.pdf | G166: Quote | H166: AT&T | L166: {"mimeType":"application/pdf","reference":{"type":"mediaSetViewItem","mediaSetViewItem":{"mediaSetRid":"ri.mio.main.media-set.7a7aadd5-adcf-42ac-9e71-12078d56f27e","mediaSetViewRid":"ri.mio.main.view.5660cab0-05c2-4700-94bc-c64529e38113","mediaItemRid":"ri.mio.main.media-item.0199713b-e2af-7291-b207-419560cb2e62"}}} | N166: PO3000196864 | P166: Equinix Canada, Ltd. | T166: FALSE | U166: -1 | AK166: ri.mio.main.media-item.0199713b-e2af-7291-b207-419560cb2e62_14_9 | AP166: AC Circuit - 230v - 20-amp - Three Phase - Redundant | AV166: ri.mio.main.media-item.0199713b-e2af-7291-b207-419560cb2e62 | AW166: Quote | BD166: POW00003 | BJ166: 0 | BL166: - | BO166: 14 | BP166: ri.mio.main.media-item.0199713b-e2af-7291-b207-419560cb2e62_13 | BT166: 1 | BU166: 9 | BV166: 100088284_OT1 | BX166: 44896 | CI166: 0 | CM166: FALSE | CN166: 39248
A167: QLI00166 | B167: ri.mio.main.media-item.0199713b-e2af-7291-b207-419560cb2e62 | C167: CAD | D167: Equinix Canada, Ltd. | F167: Quote-PO3000196864-EQUINIX-ATT+Wipro+Canada_Renewal+Post-Novation_MT1+OT1_1-222682409611+(37+months)+ATT+Signed+20230119.pdf | G167: Quote | H167: AT&T | L167: {"mimeType":"application/pdf","reference":{"type":"mediaSetViewItem","mediaSetViewItem":{"mediaSetRid":"ri.mio.main.media-set.7a7aadd5-adcf-42ac-9e71-12078d56f27e","mediaSetViewRid":"ri.mio.main.view.5660cab0-05c2-4700-94bc-c64529e38113","mediaItemRid":"ri.mio.main.media-item.0199713b-e2af-7291-b207-419560cb2e62"}}} | N167: PO3000196864 | P167: Equinix Canada, Ltd. | T167: FALSE | U167: -1 | AK167: ri.mio.main.media-item.0199713b-e2af-7291-b207-419560cb2e62_15_1 | AP167: Cross Connect | AV167: ri.mio.main.media-item.0199713b-e2af-7291-b207-419560cb2e62 | AW167: Quote | BD167: CC00001 | BJ167: 320 | BL167: 0 | BO167: 15 | BP167: ri.mio.main.media-item.0199713b-e2af-7291-b207-419560cb2e62_14 | BT167: 1 | BU167: 1 | BV167: 7-100000336087 | BX167: 44896 | CI167: 320 | CM167: FALSE | CN167: 43668
A168: QLI00167 | B168: ri.mio.main.media-item.0199713b-e2af-7291-b207-419560cb2e62 | C168: CAD | D168: Equinix Canada, Ltd. | F168: Quote-PO3000196864-EQUINIX-ATT+Wipro+Canada_Renewal+Post-Novation_MT1+OT1_1-222682409611+(37+months)+ATT+Signed+20230119.pdf | G168: Quote | H168: AT&T | L168: {"mimeType":"application/pdf","reference":{"type":"mediaSetViewItem","mediaSetViewItem":{"mediaSetRid":"ri.mio.main.media-set.7a7aadd5-adcf-42ac-9e71-12078d56f27e","mediaSetViewRid":"ri.mio.main.view.5660cab0-05c2-4700-94bc-c64529e38113","mediaItemRid":"ri.mio.main.media-item.0199713b-e2af-7291-b207-419560cb2e62"}}} | N168: PO3000196864 | P168: Equinix Canada, Ltd. | T168: FALSE | U168: -1 | AK168: ri.mio.main.media-item.0199713b-e2af-7291-b207-419560cb2e62_15_10 | AP168: Network Cable Connection - Single-Mode Fiber | AV168: ri.mio.main.media-item.0199713b-e2af-7291-b207-419560cb2e62 | AW168: Quote | BD168: CC00001 | BJ168: 320 | BO168: 15 | BP168: ri.mio.main.media-item.0199713b-e2af-7291-b207-419560cb2e62_14 | BT168: 1 | BU168: 10 | BV168: 7-100000395215 | BX168: 44896 | CI168: 320 | CM168: FALSE | CN168: 43668
A169: QLI00168 | B169: ri.mio.main.media-item.0199713b-e2af-7291-b207-419560cb2e62 | C169: CAD | D169: Equinix Canada, Ltd. | F169: Quote-PO3000196864-EQUINIX-ATT+Wipro+Canada_Renewal+Post-Novation_MT1+OT1_1-222682409611+(37+months)+ATT+Signed+20230119.pdf | G169: Quote | H169: AT&T | L169: {"mimeType":"application/pdf","reference":{"type":"mediaSetViewItem","mediaSetViewItem":{"mediaSetRid":"ri.mio.main.media-set.7a7aadd5-adcf-42ac-9e71-12078d56f27e","mediaSetViewRid":"ri.mio.main.view.5660cab0-05c2-4700-94bc-c64529e38113","mediaItemRid":"ri.mio.main.media-item.0199713b-e2af-7291-b207-419560cb2e62"}}} | N169: PO3000196864 | P169: Equinix Canada, Ltd. | T169: FALSE | U169: -1 | AK169: ri.mio.main.media-item.0199713b-e2af-7291-b207-419560cb2e62_15_11 | AP169: Cross Connect | AV169: ri.mio.main.media-item.0199713b-e2af-7291-b207-419560cb2e62 | AW169: Quote | BD169: CC00001 | BL169: 0 | BO169: 15 | BP169: ri.mio.main.media-item.0199713b-e2af-7291-b207-419560cb2e62_14 | BT169: 1 | BU169: 11 | BV169: 7-100000395213 | BX169: 44896 | CM169: FALSE | CN169: 43668
A170: QLI00169 | B170: ri.mio.main.media-item.0199713b-e2af-7291-b207-419560cb2e62 | C170: CAD | D170: Equinix Canada, Ltd. | F170: Quote-PO3000196864-EQUINIX-ATT+Wipro+Canada_Renewal+Post-Novation_MT1+OT1_1-222682409611+(37+months)+ATT+Signed+20230119.pdf | G170: Quote | H170: AT&T | L170: {"mimeType":"application/pdf","reference":{"type":"mediaSetViewItem","mediaSetViewItem":{"mediaSetRid":"ri.mio.main.media-set.7a7aadd5-adcf-42ac-9e71-12078d56f27e","mediaSetViewRid":"ri.mio.main.view.5660cab0-05c2-4700-94bc-c64529e38113","mediaItemRid":"ri.mio.main.media-item.0199713b-e2af-7291-b207-419560cb2e62"}}} | N170: PO3000196864 | P170: Equinix Canada, Ltd. | T170: FALSE | U170: -1 | AK170: ri.mio.main.media-item.0199713b-e2af-7291-b207-419560cb2e62_15_12 | AP170: Network Cable Connection - Single-Mode Fiber | AV170: ri.mio.main.media-item.0199713b-e2af-7291-b207-419560cb2e62 | AW170: Quote | BD170: CC00001 | BJ170: 320 | BO170: 15 | BP170: ri.mio.main.media-item.0199713b-e2af-7291-b207-419560cb2e62_14 | BT170: 1 | BU170: 12 | BV170: 7-100000395234 | BX170: 44896 | CI170: 320 | CM170: FALSE | CN170: 43668
...

Sheet Sheet1
A1: Item Code | B1: Unique Ones | E1: Serial Number
A2: SPC00002 | B2: ACC000001 | E2: 7-100000400339 | G2: =COUNTIFS(Sheet2!B3:B15782,E2) -> 0
A3: CAG00001 | B3: ACC00001 | E3: 0811814 | G3: =COUNTIFS(Sheet2!B4:B15783,E3) -> 0
A4: POW00001 | B4: ACC000010 | E4: 7-100000401078 | G4: =COUNTIFS(Sheet2!B5:B15784,E4) -> 0
A5: POW00003 | B5: ACC000011 | E5: 100247282.MT1 | G5: =COUNTIFS(Sheet2!B6:B15785,E5) -> 0
A6: CAB00001 | B6: ACC00008 | E6: 0204-00121279 | G6: =COUNTIFS(Sheet2!B7:B15786,E6) -> 0
A7: CAB00001 | B7: ACC00009 | E7: 0201-00121276 | G7: =COUNTIFS(Sheet2!B8:B15787,E7) -> 0
A8: CAB00001 | B8: ACC00010 | E8: 0126-00121273 | G8: =COUNTIFS(Sheet2!B9:B15788,E8) -> 0
A9: CAB00001 | B9: ACC00110 | E9: 0209-00121278 | G9: =COUNTIFS(Sheet2!B10:B15789,E9) -> 0
A10: CC00004 | B10: BA00001 | E10: 0000-00726560 | G10: =COUNTIFS(Sheet2!B11:B15790,E10) -> 0
A11: CAB00001 | B11: BUNDLE00001 | E11: 0301-00121280 | G11: =COUNTIFS(Sheet2!B12:B15791,E11) -> 0
A12: CC00001 | B12: BUNDLE00002 | E12: 7-10000394303 | G12: =COUNTIFS(Sheet2!B13:B15792,E12) -> 0
A13: CC00001 | B13: BUNDLEC0002 | E13: 100168372 | G13: =COUNTIFS(Sheet2!B14:B15793,E13) -> 1
A14: PS00004 | B14: BUNDLEE00002 | E14: 7-10000800310 | G14: =COUNTIFS(Sheet2!B15:B15794,E14) -> 0
A15: CC00001 | B15: C000001 | E15: PWP-000-1000529 | G15: =COUNTIFS(Sheet2!B16:B15795,E15) -> 0
A16: POW00003 | B16: C000004 | E16: 100247288.MT1 | G16: =COUNTIFS(Sheet2!B17:B15796,E16) -> 0
A17: PS00004 | B17: C000016 | E17: 7-10000837239 | G17: =COUNTIFS(Sheet2!B18:B15797,E17) -> 0
A18: CC00001 | B18: CA000001 | E18: PP-0303:13870772 | G18: =COUNTIFS(Sheet2!B19:B15798,E18) -> 0
A19: CC00001 | B19: CA000011 | E19: PP-0303:13870771 | G19: =COUNTIFS(Sheet2!B20:B15799,E19) -> 0
A20: POW00003 | B20: CA60001 | E20: 100247283.MT1 | G20: =COUNTIFS(Sheet2!B21:B15800,E20) -> 0
A21: POW00003 | B21: CA900001 | E21: 100245793.MT1 | G21: =COUNTIFS(Sheet2!B22:B15801,E21) -> 0
A22: POW00003 | B22: CAB000001 | E22: 100245706.MT1 | G22: =COUNTIFS(Sheet2!B23:B15802,E22) -> 0
A23: POW00003 | B23: CAB000002 | E23: 100247287.MT1 | G23: =COUNTIFS(Sheet2!B24:B15803,E23) -> 0
A24: POW00003 | B24: CAB00001 | E24: 100245700.MT1 | G24: =COUNTIFS(Sheet2!B25:B15804,E24) -> 0
A25: POW00003 | B25: CAB00002 | E25: 100247281.MT1 | G25: =COUNTIFS(Sheet2!B26:B15805,E25) -> 0
A26: POW00003 | B26: CAB0001 | E26: 100245795.MT1 | G26: =COUNTIFS(Sheet2!B27:B15806,E26) -> 0
A27: 20008-LEP-005.1 | B27: CAG000001 | G27: =COUNTIFS(Sheet2!B28:B15807,E27) -> 0
A28: 20008-LEP-005.1 | B28: CAG00001 | E28: 0216-00087170 | G28: =COUNTIFS(Sheet2!B29:B15808,E28) -> 1
B29: CAG00002 | E29: 0225-00087179 | G29: =COUNTIFS(Sheet2!B30:B15809,E29) -> 1
A30: CAB00001 | B30: CAG000042 | E30: 0226-00087180 | G30: =COUNTIFS(Sheet2!B31:B15810,E30) -> 1
A31: CAB00001 | B31: CAG00005 | E31: 113995-00078068 | G31: =COUNTIFS(Sheet2!B32:B15811,E31) -> 0
A32: CAB00001 | B32: CAG00006 | E32: 7-10000022957 | G32: =COUNTIFS(Sheet2!B33:B15812,E32) -> 0
A33: CAG00001 | B33: CAG00007 | E33: 100088053.OT1 | G33: =COUNTIFS(Sheet2!B34:B15813,E33) -> 0
A34: POW00003 | B34: CAG00008 | E34: 100088054.OT1 | G34: =COUNTIFS(Sheet2!B35:B15814,E34) -> 0
A35: POW00003 | B35: CAG0001 | E35: 100088057.OT1 | G35: =COUNTIFS(Sheet2!B36:B15815,E35) -> 0
A36: POW00003 | B36: CAQ00001 | E36: 100088058.OT1 | G36: =COUNTIFS(Sheet2!B37:B15816,E36) -> 0
A37: POW00003 | B37: CAQ0001 | E37: 100088059.OT1 | G37: =COUNTIFS(Sheet2!B38:B15817,E37) -> 0
A38: POW00003 | B38: CC000001 | E38: 100088060.OT1 | G38: =COUNTIFS(Sheet2!B39:B15818,E38) -> 0
A39: POW00003 | B39: CC00001 | E39: 0217-00087171 | G39: =COUNTIFS(Sheet2!B40:B15819,E39) -> 1
A40: POW00003 | B40: CC000011 | E40: 100088061.OT1 | G40: =COUNTIFS(Sheet2!B41:B15820,E40) -> 0
A41: CAB00001 | B41: CC00002 | E41: 100088062.OT1 | G41: =COUNTIFS(Sheet2!B42:B15821,E41) -> 0
... A145: POW00003 | B145: POW00033 | E145: 7-10000497724 | G145: =COUNTIFS(Sheet2!B146:B15925,E145) -> 0
A146: CAB00001 | B146: POW0010 | E146: 1000041390 | G146: =COUNTIFS(Sheet2!B147:B15926,E146) -> 0
A147: CAB00001 | B147: PPP00001 | E147: 7-10000396651 | G147: =COUNTIFS(Sheet2!B148:B15927,E147) -> 0
A148: CC00001 | B148: PPP00002 | E148: 1000099154 | G148: =COUNTIFS(Sheet2!B149:B15928,E148) -> 0
A149: CC00001 | B149: PQW00001 | E149: 7-10000395955 | G149: =COUNTIFS(Sheet2!B150:B15929,E149) -> 0
A150: CC00001 | B150: PS000001 | E150: 1000099591 | G150: =COUNTIFS(Sheet2!B151:B15930,E150) -> 0
A151: CC00001 | B151: PS000002 | E151: 7-10000395958 | G151: =COUNTIFS(Sheet2!B152:B15931,E151) -> 0
A152: CC00001 | B152: PS000003 | E152: 1000099592 | G152: =COUNTIFS(Sheet2!B153:B15932,E152) -> 0
A153: CC00001 | B153: PS00001 | E153: 100088284_OT1 | G153: =COUNTIFS(Sheet2!B154:B15933,E153) -> 0
A154: CC00001 | B154: PS00002 | E154: 7-10000398599 | G154: =COUNTIFS(Sheet2!B155:B15934,E154) -> 0
A155: CC00001 | B155: PS00003 | E155: 1000143089 | G155: =COUNTIFS(Sheet2!B156:B15935,E155) -> 0
A156: POW00003 | B156: PS000033 | E156: 7-10000395913 | G156: =COUNTIFS(Sheet2!B157:B15936,E156) -> 0
A157: CC00001 | B157: PS00004 | E157: 1000091511 | G157: =COUNTIFS(Sheet2!B158:B15937,E157) -> 0
A158: CC00001 | B158: PS00005 | E158: 100088279_OT1 | G158: =COUNTIFS(Sheet2!B159:B15938,E158) -> 0
A159: CC00001 | B159: PS0001 | E159: 100088300_OT1 | G159: =COUNTIFS(Sheet2!B160:B15939,E159) -> 0
A160: CC00001 | B160: PS00012 | E160: 100088323_OT1 | G160: =COUNTIFS(Sheet2!B161:B15940,E160) -> 0
A161: POW00003 | B161: PS00021 | E161: 100088280_OT1 | G161: =COUNTIFS(Sheet2!B162:B15941,E161) -> 0
A162: POW00003 | B162: PS00022 | E162: 7-100000336087 | G162: =COUNTIFS(Sheet2!B163:B15942,E162) -> 0
A163: POW00003 | B163: PS00033 | E163: 7-100000395215 | G163: =COUNTIFS(Sheet2!B164:B15943,E163) -> 0
A164: POW00003 | B164: PS00040 | E164: 7-100000395213 | G164: =COUNTIFS(Sheet2!B165:B15944,E164) -> 0
A165: POW00003 | B165: PS00043 | E165: 7-100000395234 | G165: =COUNTIFS(Sheet2!B166:B15945,E165) -> 0
A166: POW00003 | B166: PS00046 | E166: 7-100000395235 | G166: =COUNTIFS(Sheet2!B167:B15946,E166) -> 0
A167: CC00001 | B167: PSS00021 | E167: 100095223 | G167: =COUNTIFS(Sheet2!B168:B15947,E167) -> 0
A168: CC00001 | B168: PW000001 | E168: 7-100000395089 | G168: =COUNTIFS(Sheet2!B169:B15948,E168) -> 0
A169: CC00001 | B169: PW00001 | E169: 100095189 | G169: =COUNTIFS(Sheet2!B170:B15949,E169) -> 0
A170: CC00001 | B170: SIP00001 | E170: 7-100000393787 | G170: =COUNTIFS(Sheet2!B171:B15950,E170) -> 0
A171: CC00001 | B171: SP0C0006 | E171: 100093197 | G171: =COUNTIFS(Sheet2!B172:B15951,E171) -> 0
A172: CC00001 | B172: SPC00001 | E172: 7-100000393786 | G172: =COUNTIFS(Sheet2!B173:B15952,E172) -> 0
A173: CC00001 | B173: SPC00002 | E173: 100096522 | G173: =COUNTIFS(Sheet2!B174:B15953,E173) -> 0
A174: CC00001 | B174: SPC00003 | E174: 100095186 | G174: =COUNTIFS(Sheet2!B175:B15954,E174) -> 0
A175: CC00001 | B175: SPC00006 | E175: 7-100000390847 | G175: =COUNTIFS(Sheet2!B176:B15955,E175) -> 0
A176: CC00001 | B176: SPC00009 | E176: 7-100000390937 | G176: =COUNTIFS(Sheet2!B177:B15956,E176) -> 0
A177: CC00001 | B177: SPC0006 | E177: 7-100000392316 | G177: =COUNTIFS(Sheet2!B178:B15957,E177) -> 0
A178: CC00001 | B178: SPCC0006 | E178: 100095310 | G178: =COUNTIFS(Sheet2!B179:B15958,E178) -> 0
A179: CC00001 | B179: SPOC00002 | E179: 7-100000392315 | G179: =COUNTIFS(Sheet2!B180:B15959,E179) -> 0
A180: CC00001 | B180: TERMINATION | E180: 7-100000389531 | G180: =COUNTIFS(Sheet2!B181:B15960,E180) -> 0
A181: CC00001 | E181: 100099512 | G181: =COUNTIFS(Sheet2!B182:B15961,E181) -> 1
A182: CC00001 | E182: 7-100000392870 | G182: =COUNTIFS(Sheet2!B183:B15962,E182) -> 0
A183: CC00001 | E183: 100043091 | G183: =COUNTIFS(Sheet2!B184:B15963,E183) -> 1
A184: CC00001 | E184: 7-100000399512 | G184: =COUNTIFS(Sheet2!B185:B15964,E184) -> 0
A185: CC00001 | E185: 22278457 | G185: =COUNTIFS(Sheet2!B186:B15965,E185) -> 0
A186: CC00001 | E186: 100048497 | G186: =COUNTIFS(Sheet2!B187:B15966,E186) -> 0
A187: CC00001 | E187: 100099507 | G187: =COUNTIFS(Sheet2!B188:B15967,E187) -> 1
A188: CC00001 | E188: 7-100000395176 | G188: =COUNTIFS(Sheet2!B189:B15968,E188) -> 0
A189: CC00001 | E189: 7-100000690586 | G189: =COUNTIFS(Sheet2!B190:B15969,E189) -> 0
A190: CC00001 | E190: 7-100000495469 | G190: =COUNTIFS(Sheet2!B191:B15970,E190) -> 0
A191: CC00001 | E191: 1000431766 | G191: =COUNTIFS(Sheet2!B192:B15971,E191) -> 0
A192: CC00001 | E192: 7-100000395216 | G192: =COUNTIFS(Sheet2!B193:B15972,E192) -> 0
A193: CC00001 | E193: 22278550 | G193: =COUNTIFS(Sheet2!B194:B15973,E193) -> 0
A194: CC00001 | E194: 100084898 | G194: =COUNTIFS(Sheet2!B195:B15974,E194) -> 1
A195: CC00001 | E195: 22278543 | G195: =COUNTIFS(Sheet2!B196:B15975,E195) -> 0
A196: CC00001 | E196: 100084913 | G196: =COUNTIFS(Sheet2!B197:B15976,E196) -> 1
A197: CC00001 | E197: 7-10000399557 | G197: =COUNTIFS(Sheet2!B198:B15977,E197) -> 0
A198: CC00001 | E198: 100099518 | G198: =COUNTIFS(Sheet2!B199:B15978,E198) -> 1
A199: CC00001 | E199: CP-2001:100018154 | G199: =COUNTIFS(Sheet2!B200:B15979,E199) -> 0
A200: CC00001 | E200: PP-0302:10084393 | G200: =COUNTIFS(Sheet2!B201:B15980,E200) -> 0
A201: CC00001 | E201: 7-10000798743 | G201: =COUNTIFS(Sheet2!B202:B15981,E201) -> 0
A202: CC00001 | E202: PP-2004:10051034 | G202: =COUNTIFS(Sheet2!B203:B15982,E202) -> 0
A203: CC00001 | E203: 7-10000799283 | G203: =COUNTIFS(Sheet2!B204:B15983,E203) -> 0
...

Sheet Sheet2
B3: 23255328
B4: 23254510
B5: 23254558
B6: 23255333
B7: ANT:0205:1299536
B8: ANT:0204:1299537
B9: ANT:0708:1128198
B10: ANT:0102:1171730
B11: ANT:2303:1171705
B12: 23247655
B13: ANT:2308:1100576
B14: 23247662
B15: 23254720
B16: 23254717
B17: ANT:0103:1299605
B18: ANT:0102:1299643
B19: 23255313
B20: ANT:0101:1302165
B21: 23255440
B22: 0220-22730038
B23: 0320-22742153
B24: 0319-22742150
B25: 0219-22730035
B26: 0106-21178082
B27: 0103-21178083
B28: 0202-20449865
B29: 0201-21267825
B30: 0112-22177009
B31: 0102-21178070
B32: 0104-21178081
B33: 0105-21178085
... B342: 0207-20938274
B343: 100144616
B344: 0000-21891100
B345: 0104-21920581
B346: 0204-21920602
B347: 0311-21920579
B348: 0209-21920607
B349: 0202-21920600
B350: 0309-21920590
B351: 0001-21930026
B352: 0108-21920585
B353: 0102-21920592
B354: 0301-21920594
B355: 0201-21920599
... B2185: 010504-22879302
B2186: 22177012
B2187: 010501-21178066
B2188: 030102-21267824
B2189: 21773013
B2190: 030102-20449864
B2191: 110257-21266107
B2192: 020281-21665324
B2193: 21404673
B2194: 020259-22226417
B2195: 050141-21258527
B2196: 000Z3A-22462381
B2197: 000Z1I-21064415
B2198: 21408777
B2199: 22395644
B2200: 035320-23115960
B2201: 21415907
B2202: 022326-22766448
B2203: 020900-21024856
B2204: 034545-20782567
B2205: 421125-21138194
B2206: 421125-21001434
B2207: 422460-23028972
B2208: 421125-21188681
B2209: 22021480
B2210: 000040-23143073
B2211: 21887246
B2212: 000990-21027263
B2213: 22482930
B2214: 22386534
B2215: 000540-22621435
B2216: 000435-20316104
B2217: 21615659
B2218: 21613482
B2219: 03100-12747981
B2220: 22311757
B2221: 22090039
B2222: 22134009
B2223: 324100-22739880
B2224: 314515-22497539
B2225: 22192307
B2226: 032575-21669570
B2227: 033250-22995053
B2228: 21957864
B2229: 314305-20901623
B2230: 032195-20880033
B2231: 033595-21110448
B2232: 324610-22926628
B2233: 032670-22787967
B2234: 21732124
B2235: 033595-21100240
B2236: 032630-22739881
B2237: 22061466
B2238: 22448726
B2239: 032220-21857901
...
